Workbook

Sheet Guía de uso
A1: INSTRUCCIONES DE USO
A6: Para el uso correcto de esta herramienta, usted debe: | Y6: 0 | AA6: =+CONCATENATE($A$20," ",#REF!," = ",#REF!) -> #REF!
A7: OBJETIVO | Y7: 1 | AA7: =+CONCATENATE($A$20," ",$A$21," = ",$B$21) -> Nivel 1 = Inicial
A8: Este documento tiene como objetivo servir como una guía exhaustiva y detallada para la implementación, mantenimiento y mejora continua de un Sistema de Gestión de Seguridad de la Información (SGSI). Además, facilita la evaluación del nivel de madurez del SGSI en alineación con la norma ISO 27001:2022, al proporcionar una herramienta integral que apoya a las organizaciones en la gestión eficaz y robusta de la seguridad de la información, garantizando la confidencialidad, integridad y disponibilidad de sus activos. | Y8: 2 | AA8: =+CONCATENATE($A$20," ",$A$22," = ",$B$22) -> Nivel 2 = Repetible
Y9: 3 | AA9: =+CONCATENATE($A$20," ",$A$23," = ",$B$23) -> Nivel 3 = Definido
Y10: 4 | AA10: =+CONCATENATE($A$20," ",$A$24," = ",$B$24) -> Nivel 4 = Gestionado
A11: ALCANCE | Y11: 5 | AA11: =+CONCATENATE($A$20," ",#REF!," = ",#REF!) -> #REF!
A12: Mediante el uso de una tabla de evaluación de madurez, este documento ayudará a identificar el nivel de madurez del Sistemas de gestión de seguridad de la información y proporcionará recomendaciones específicas para alcanzar niveles superiores. Esta herramienta no pretende ser exhaustiva, sino proporcionar una base sólida para el análisis y la toma de decisiones.
A13: INSTRUCCIONES DE USO
A15: Personalización de niveles de madurez
A16: En el siguiente cuadro podrá personalizar los niveles, de manera determinada visualizará del 0 al 4, y la descripción y definición correspondiente, podrá realizar la modificación de la columna de "Descripción" a adjetivos relacionados a su organización, como por ejemplo, "gestionado" por "administrado", etc.
A20: Nivel | B20: Descripción | C20: Definición
A21: 1 | B21: Inicial | C21: Los procesos de gestión de la seguridad de la información no están documentados ni formalizados. Las actividades relacionadas con la seguridad de la información se llevan a cabo de manera ad-hoc y reactiva, respondiendo a incidentes y problemas a medida que surgen sin un enfoque estructurado.
A22: 2 | B22: Repetible | C22: Los procesos de gestión de la seguridad de la información están documentados y existe un esfuerzo por seguir una metodología básica. Sin embargo, la implementación de estos procesos es inconsistente y depende en gran medida de individuos específicos.
A23: 3 | B23: Definido | C23: Los procesos de gestión de la seguridad de la información están bien documentados y definidos. La organización sigue metodologías estándar y existe un nivel básico de control y supervisión.
A24: 4 | B24: Gestionado | C24: La gestión de la seguridad de la información está bien integrada en la mayoría de los procesos de la organización. Los procesos están controlados y supervisados regularmente, utilizando métricas y KPIs para evaluar su efectividad.
A26: 1. Checklist - Contexto, liderazgo, planificación, soporte, operación, evaluación y mejora
A27: En estas hojas, en la columna "G" podrá marcar o seleccionar el nivel al cual corresponde el estado actual del cumplimiento de cada uno de los aspectos:
A28: RECUERDE: No seleccione dos niveles, ya que puede afectar el correcto funcionamiento de la herramienta y la evaluación del nivel actual
A29: Al seleccionar el nivel, de manera automática se resaltará el enunciado
A36: 2. Resumen y valoración
A37: De acuerdo con la información ingresada en las hojas de "Checklist" de cada aspecto, visualizará un resumen de cada uno de los niveles seleccionados.
A40: A continuación, visualice la estructura de esta hoja:
A52: 1. Aspectos: En esta columna visualizará el listado de los aspectos a tener en cuenta según la ISO 27001:2022
A53: 2. Nivel actual: En esta columna podrá detallar cuál fue el nivel seleccionado en cada aspecto a tener en cuenta.
A54: 2. Puntaje promedio nivel actual: En estas dos celdas visualizará el puntaje del nivel actual tanto cualitativamente como cuantitativamente respecto al promedio de las calificaciones de cada uno de los aspectos.
A55: 4. Riesgo: Seleccione en esta columna la valoración del riesgo para cada aspecto, además podrá describir el riesgo en detalle.
A58: A continuación, visualice la estructura de esta hoja:
... A69: En la última pestaña de este documento, visualizará de manera gráfica el estado actual del sistema de gestión del riesgo y seguridad en la organización, según la norma ISO 27001:2022. Esta hoja tiene como objetivo proporcionar una representación visual clara y comprensible de los resultados de la evaluación, destacando las áreas de fortaleza y las oportunidades de mejora. A través de gráficos y diagrama de telaraña, los usuarios pueden identificar rápidamente el nivel de madurez en diferentes aspectos de la gestión del riesgo, facilitando la comunicación de los resultados a las partes interesadas y apoyando la toma de decisiones estratégicas para avanzar hacia niveles superiores de madurez.
A74: De color azul | B74: visualizará el nivel óptimo, de manera predeterminada, es de 4.
A75: De color naranja | B75: visualizará el estado actual de los aspectos a evaluar según la norma ISO 27001:2022, de manera predeterminada el nivel óptimo es de 4.
A77: RECOMENDACIONES DE USO
A78: No modifique la formulación o estructura del documento. Si tiene cualquier duda o inquietud sobre su funcionamiento, lo invitamos a comunicarse por medio de nuestro correo electrónico: info@auditool.org
B81: Autor: Equipo Auditool | I81: info@auditool.org

Sheet Check - Contexto
B1: Herramienta para medir el nivel actual de los Sistemas de gestión de seguridad de la información según ISO 27001:2022
A5: Entidad (o cliente): | C5: ID. | D5: Período de auditoría de: 1/01/2023 | E5: Hasta: 31/12/2023 | G5: Referencia
A6: Preparado por: | D6: Revisado por: | G6: XX-XX
A7: Supervisado por: | D7: Aprobado por:
A10: OBJETIVO
A11: Esta herramienta permite evaluar y asegurar el estado actual de la implementación, mantenimiento y mejora del sistema de gestión de la seguridad de la información (SGSI) según la norma ISO 27001:2022, y determinar si está integrado y aplicado de manera efectiva en la organización. Esto incluye verificar que la seguridad de la información está gestionada de forma sistemática, adaptada a las necesidades organizacionales, y en mejora continua.
A12: ALCANCE
A13: El contexto de la organización es un aspecto crucial en la implementación y mantenimiento de un sistema de gestión de la seguridad de la información (SGSI) conforme a la norma ISO 27001:2022. Comprender el contexto en el que opera la organización permite identificar y gestionar eficazmente los riesgos y oportunidades relacionados con la seguridad de la información.
A14: CHECKLIST ISO 27001 - CONTEXTO DE LA ORGANIZACIÓN
A15: 1.1 Entender la organización y su contexto: Para establecer un SGSI efectivo, la organización debe identificar los problemas externos e internos que son relevantes para su propósito y que pueden afectar su capacidad para lograr los resultados esperados. Esto implica un análisis profundo de factores como el entorno económico, social, tecnológico, ambiental, legal y cultural en el que opera la organización. | G15: =IF(COUNTIF(G17:G20,TRUE)>1,"SELECCIONE SOLAMENTE UN NIVEL","Marque la opción que describa mejor la situación actual del contexto de la organización ") -> Marque la opción que describa mejor la situación actual del contexto de la organización
A16: Nivel | B16: Detalle | D16: Descripción | F16: Características
A17: =+'Guía de uso'!$AA$7 -> Nivel 1 = Inicial | B17: No se realizan esfuerzos documentados para comprender el contexto organizacional. | D17: Las actividades se llevan a cabo sin un enfoque estructurado y carecen de documentación formal. | F17: Falta de documentación. Acciones reactivas. No hay evaluación del contexto externo o interno. | G17: FALSE | J17: =+IF(G17=TRUE,'Guía de uso'!$Y$7,0) -> 0
A18: =+'Guía de uso'!$AA$8 -> Nivel 2 = Repetible | B18: Los procesos básicos están documentados, pero su aplicación es irregular y depende de individuos clave. | D18: Existen esfuerzos por documentar los procesos, pero la implementación es inconsistente y no sistemática. | F18: Documentación básica. Implementación inconsistente. Dependencia de individuos específicos para la evaluación del contexto. | G18: TRUE | J18: =+IF(G18=TRUE,'Guía de uso'!$Y$8,0) -> 2
A19: =+'Guía de uso'!$AA$9 -> Nivel 3 = Definido | B19: Se utilizan metodologías estandarizadas y los procesos están documentados y definidos. | D19: Los procesos están bien documentados y se siguen metodologías estándar, con un nivel básico de control y supervisión. | F19: Documentación clara y definida. Uso de metodologías estándar. Evaluación regular del contexto organizacional. | G19: FALSE | J19: =+IF(G19=TRUE,'Guía de uso'!$Y$9,0) -> 0
A20: =+'Guía de uso'!$AA$10 -> Nivel 4 = Gestionado | B20: El contexto organizacional se integra en los procesos, con controles y supervisión regulares mediante KPIs. | D20: La evaluación del contexto está integrada en los procesos organizacionales, con monitoreo continuo y uso de métricas y KPIs para asegurar la efectividad y mejora. | F20: Integración completa en los procesos de la organización. Control y supervisión continuos. Uso de métricas y KPIs para la evaluación y mejora continua. | G20: FALSE | J20: =+IF(G20=TRUE,'Guía de uso'!$Y$10,0) -> 0
A21: 1.2. Comprender las necesidades y expectativas de las partes interesadas: La organización debe determinar las partes interesadas que son relevantes para su SGSI, así como sus requisitos. Esto incluye no solo los requisitos legales y reglamentarios, sino también las expectativas y necesidades de clientes, proveedores, empleados y otras partes interesadas. | G21: =IF(COUNTIF(G23:G26,TRUE)>1,"SELECCIONE SOLAMENTE UN NIVEL","Marque la opción que describa mejor la situación actual del contexto de la organización ") -> Marque la opción que describa mejor la situación actual del contexto de la organización
A22: Nivel | B22: Detalle | D22: Descripción | F22: Características
A23: =+'Guía de uso'!$AA$7 -> Nivel 1 = Inicial | B23: No se identifican ni documentan las necesidades de las partes interesadas. | D23: Las actividades relacionadas con la identificación de necesidades de partes interesadas son reactivas y sin documentación formal. | F23: Ausencia de identificación de partes interesadas. Falta de documentación de necesidades. Actividades ad-hoc y reactivas. | G23: FALSE | J23: =+IF(G23=TRUE,'Guía de uso'!$Y$7,0) -> 0
A24: =+'Guía de uso'!$AA$8 -> Nivel 2 = Repetible | B24: Existen intentos documentados de identificación, pero su ejecución es inconsistente. | D24: Hay esfuerzos por identificar y documentar las necesidades de las partes interesadas, pero estos son irregulares y dependen de ciertos individuos. | F24: Intentos básicos de documentación. Ejecución irregular y dependiente de individuos específicos. Esfuerzos iniciales por identificar necesidades de partes interesadas. | G24: FALSE | J24: =+IF(G24=TRUE,'Guía de uso'!$Y$8,0) -> 0
A25: =+'Guía de uso'!$AA$9 -> Nivel 3 = Definido | B25: Procesos documentados y metodologías estándar aseguran la identificación y entendimiento adecuados. | D25: La identificación y documentación de las necesidades de las partes interesadas se realiza de manera consistente, siguiendo metodologías estándar. | F25: Procesos bien documentados. Uso de metodologías estándar para la identificación de necesidades. Evaluación y documentación regular de las expectativas de las partes interesadas. | G25: TRUE | J25: =+IF(G25=TRUE,'Guía de uso'!$Y$9,0) -> 3
A26: =+'Guía de uso'!$AA$10 -> Nivel 4 = Gestionado | B26: La identificación de necesidades está plenamente integrada, con monitoreo regular y uso de métricas. | D26: La identificación y evaluación de las necesidades de las partes interesadas está integrada en los procesos organizacionales, con monitoreo continuo y uso de KPIs. | F26: Integración completa en los procesos organizacionales. Monitoreo y control regulares. Evaluación continua mediante métricas y KPIs para asegurar la satisfacción de las partes interesadas. | G26: FALSE | J26: =+IF(G26=TRUE,'Guía de uso'!$Y$10,0) -> 0
A27: 1.3. Determinación del alcance del Sistema de Gestión de Seguridad de la Información: Definir claramente el alcance del SGSI es fundamental para su eficacia. La organización debe determinar los límites y la aplicabilidad del SGSI, considerando los factores internos y externos identificados así como los requisitos de las partes interesadas. | G27: =IF(COUNTIF(G29:G32,TRUE)>1,"SELECCIONE SOLAMENTE UN NIVEL","Marque la opción que describa mejor la situación actual del contexto de la organización ") -> Marque la opción que describa mejor la situación actual del contexto de la organización
A28: Nivel | B28: Detalle | D28: Descripción | F28: Características
A29: =+'Guía de uso'!$AA$7 -> Nivel 1 = Inicial | B29: No se determina ni formaliza el alcance del SGSI. Las actividades son reactivas y no estructuradas. | D29: No hay esfuerzos documentados para establecer el alcance del SGSI, resultando en actividades ad-hoc y sin una dirección clara. | F29: Ausencia de documentación. Actividades reactivas y no estructuradas. Falta de determinación del alcance del SGSI. | G29: FALSE | J29: =+IF(G29=TRUE,'Guía de uso'!$Y$7,0) -> 0
A30: =+'Guía de uso'!$AA$8 -> Nivel 2 = Repetible | B30: El alcance del SGSI está documentado, pero su implementación depende en gran medida de personas específicas. | D30: Existen esfuerzos para documentar el alcance del SGSI, pero la implementación es inconsistente y depende de individuos específicos. | F30: Documentación básica. Implementación irregular y dependiente de individuos específicos. Esfuerzos iniciales por determinar el alcance del SGSI. | G30: FALSE | J30: =+IF(G30=TRUE,'Guía de uso'!$Y$8,0) -> 0
A31: =+'Guía de uso'!$AA$9 -> Nivel 3 = Definido | B31: El alcance del SGSI está bien documentado y definido, siguiendo metodologías estándar. | D31: La documentación del alcance del SGSI es clara y sigue metodologías estándar, con un nivel básico de control y supervisión para asegurar su efectividad. | F31: Alcance bien definido y documentado. Uso de metodologías estándar. Evaluación y documentación regular del alcance del SGSI. | G31: TRUE | J31: =+IF(G31=TRUE,'Guía de uso'!$Y$9,0) -> 3
A32: =+'Guía de uso'!$AA$10 -> Nivel 4 = Gestionado | B32: El alcance del SGSI está completamente integrado y supervisado regularmente con métricas y KPIs. | D32: La determinación del alcance del SGSI está integrada en los procesos organizacionales, con monitoreo continuo y uso de métricas y KPIs para asegurar la efectividad. | F32: Integración completa en los procesos de la organización. Control y supervisión continuos. Uso de métricas y KPIs para la evaluación y mejora continua del alcance del SGSI. | G32: FALSE | J32: =+IF(G32=TRUE,'Guía de uso'!$Y$10,0) -> 0
A33: 1.4. Sistema de Gestión de Seguridad de la Información: Una vez definido el contexto y el alcance, la organización debe establecer, implementar, mantener y mejorar continuamente un SGSI que incluya los procesos necesarios y sus interacciones. Esto garantiza que el SGSI esté plenamente integrado en las operaciones de la organización y que pueda adaptarse a los cambios en el contexto interno y externo. | G33: =IF(COUNTIF(G35:G38,TRUE)>1,"SELECCIONE SOLAMENTE UN NIVEL","Marque la opción que describa mejor la situación actual del contexto de la organización ") -> Marque la opción que describa mejor la situación actual del contexto de la organización
A34: Nivel | B34: Detalle | D34: Descripción | F34: Características
A35: =+'Guía de uso'!$AA$7 -> Nivel 1 = Inicial | B35: No existe un SGSI documentado; las acciones son reactivas y no estructuradas. | C35: No existe un SGSI documentado; las acciones son reactivas y no estructuradas. | D35: Las actividades relacionadas con el SGSI son ad-hoc y no documentadas, resultando en una gestión desorganizada y reactiva. | F35: Ausencia de documentación del SGSI. Actividades reactivas y no estructuradas. Falta de dirección clara en la gestión de la seguridad de la información. | G35: FALSE | J35: =+IF(G35=TRUE,'Guía de uso'!$Y$7,0) -> 0
A36: =+'Guía de uso'!$AA$8 -> Nivel 2 = Repetible | B36: El SGSI está documentado, pero su aplicación es inconsistente y varía según el individuo. | C36: El SGSI está documentado, pero su aplicación es inconsistente y varía según el individuo. | D36: Existen esfuerzos por documentar el SGSI, pero la implementación es inconsistente y depende en gran medida de individuos específicos para su aplicación efectiva. | F36: Documentación básica del SGSI. Implementación irregular y dependiente de individuos específicos. Esfuerzos iniciales por formalizar el SGSI. | G36: TRUE | J36: =+IF(G36=TRUE,'Guía de uso'!$Y$8,0) -> 2
A37: =+'Guía de uso'!$AA$9 -> Nivel 3 = Definido | B37: SGSI bien definido y documentado, con control y supervisión básica siguiendo metodologías estándar. | C37: SGSI bien definido y documentado, con control y supervisión básica siguiendo metodologías estándar. | D37: La documentación y definición del SGSI es clara, siguiendo metodologías estándar con un nivel básico de control y supervisión para asegurar la efectividad. | F37: SGSI bien definido y documentado. Uso de metodologías estándar. Control y supervisión básica del SGSI. | G37: FALSE | J37: =+IF(G37=TRUE,'Guía de uso'!$Y$9,0) -> 0
A38: =+'Guía de uso'!$AA$10 -> Nivel 4 = Gestionado | B38: El SGSI está completamente integrado en los procesos, con controles, supervisión regular y evaluación con KPIs. | C38: El SGSI está completamente integrado en los procesos, con controles, supervisión regular y evaluación con KPIs. | D38: La gestión del SGSI está integrada en los procesos organizacionales, con monitoreo continuo y uso de métricas y KPIs para asegurar la efectividad y mejora continua. | F38: Integración completa del SGSI en los procesos de la organización. Control y supervisión continuos. Uso de métricas y KPIs para la evaluación y mejora continua del SGSI. | G38: FALSE | J38: =+IF(G38=TRUE,'Guía de uso'!$Y$10,0) -> 0
A40: CONCLUSIÓN Y/O OBSERVACIONES ADICIONALES

Sheet Check - Liderazgo
B1: Herramienta para medir el nivel actual de los Sistemas de gestión de seguridad de la información según ISO 27001:2022
A5: Entidad (o cliente): | C5: ID. | D5: Período de auditoría de: 1/01/2023 | E5: Hasta: 31/12/2023 | G5: Referencia
A6: Preparado por: | D6: Revisado por: | G6: XX-XX
A7: Supervisado por: | D7: Aprobado por:
A10: OBJETIVO
A11: Esta herramienta permite evaluar y asegurar el estado actual de la implementación, mantenimiento y mejora del sistema de gestión de la seguridad de la información (SGSI) según la norma ISO 27001:2022, y determinar si está integrado y aplicado de manera efectiva en la organización. Esto incluye verificar que la seguridad de la información está gestionada de forma sistemática, adaptada a las necesidades organizacionales, y en mejora continua.
A12: ALCANCE
A13: El liderazgo es un componente esencial para el éxito de un sistema de gestión de la seguridad de la información (SGSI) según la norma ISO 27001:2022. La alta dirección tiene la responsabilidad de establecer una visión clara y un compromiso firme con la seguridad de la información, asegurando que esté integrada en todos los niveles de la organización.
A14: CHECKLIST ISO 27001 - LIDERAZGO
A15: 2.1 Liderazgo y compromiso: La alta dirección debe demostrar liderazgo y compromiso con respecto al SGSI mediante diversas acciones. Estas incluyen garantizar que la política de seguridad de la información y los objetivos asociados estén alineados con la dirección estratégica de la organización, y que los requisitos del SGSI se integren en los procesos de la organización. | G15: =IF(COUNTIF(G17:G20,TRUE)>1,"SELECCIONE SOLAMENTE UN NIVEL","Marque la opción que describa mejor la situación actual del liderazgo") -> Marque la opción que describa mejor la situación actual del liderazgo
A16: Nivel | B16: Detalle | D16: Descripción | F16: Características
A17: =+'Guía de uso'!$AA$7 -> Nivel 1 = Inicial | B17: La alta dirección no demuestra un compromiso formalizado con el SGSI. | D17: No hay evidencia de un compromiso estructurado por parte de la alta dirección para apoyar y liderar el SGSI. | F17: Ausencia de compromiso formalizado. Falta de liderazgo claro en seguridad de la información. Actividades reactivas y no estructuradas. | G17: FALSE | J17: =+IF(G17=TRUE,'Guía de uso'!$Y$7,0) -> 0
A18: =+'Guía de uso'!$AA$8 -> Nivel 2 = Repetible | B18: La alta dirección muestra un compromiso básico y existen esfuerzos documentados, aunque irregulares. | D18: Existen esfuerzos documentados para demostrar el compromiso de la alta dirección, pero la aplicación es inconsistente. | F18: Compromiso básico documentado. Implementación irregular. Dependencia de individuos específicos para liderar las iniciativas de seguridad. | G18: TRUE | J18: =+IF(G18=TRUE,'Guía de uso'!$Y$8,0) -> 2
A19: =+'Guía de uso'!$AA$9 -> Nivel 3 = Definido | B19: El compromiso de la alta dirección está bien documentado y sigue metodologías estándar con control básico. | D19: La alta dirección demuestra un compromiso claro y documentado, siguiendo metodologías estándar y asegurando un nivel básico de control y supervisión. | F19: Compromiso claro y documentado. Uso de metodologías estándar. Control y supervisión básica del compromiso de la alta dirección. | G19: FALSE | J19: =+IF(G19=TRUE,'Guía de uso'!$Y$9,0) -> 0
A20: =+'Guía de uso'!$AA$10 -> Nivel 4 = Gestionado | B20: El compromiso de la alta dirección está completamente integrado, con supervisión regular y uso de métricas para evaluar su efectividad. | D20: La alta dirección está plenamente integrada en los procesos de seguridad, con monitoreo continuo y uso de métricas y KPIs para evaluar y mejorar su compromiso. | F20: Integración completa del compromiso de la alta dirección en los procesos. Supervisión y control regulares. Uso de métricas y KPIs para evaluar el compromiso. | G20: FALSE | J20: =+IF(G20=TRUE,'Guía de uso'!$Y$10,0) -> 0
A21: 2.2 Política: La alta dirección debe establecer una política de seguridad de la información que sea apropiada para el propósito de la organización y que incluya objetivos claros. Esta política debe reflejar el compromiso de la organización de cumplir con los requisitos aplicables y de mejorar continuamente el SGSI. | G21: =IF(COUNTIF(G23:G26,TRUE)>1,"SELECCIONE SOLAMENTE UN NIVEL","Marque la opción que describa mejor la situación actual del liderazgo") -> Marque la opción que describa mejor la situación actual del liderazgo
A22: Nivel | B22: Detalle | D22: Descripción | F22: Características
A23: =+'Guía de uso'!$AA$7 -> Nivel 1 = Inicial | B23: No se ha establecido una política de seguridad de la información formalizada. | D23: Las actividades de seguridad se realizan sin una política definida, resultando en una falta de dirección clara y coherencia en las acciones de seguridad. | F23: Ausencia de política formal. Actividades de seguridad sin dirección clara. Falta de coherencia en las acciones de seguridad. | G23: FALSE | J23: =+IF(G23=TRUE,'Guía de uso'!$Y$7,0) -> 0
A24: =+'Guía de uso'!$AA$8 -> Nivel 2 = Repetible | B24: Existe una política básica de seguridad de la información, pero su implementación es inconsistente. | D24: Se ha establecido una política de seguridad, pero la aplicación y el seguimiento son irregulares y dependen de individuos específicos. | F24: Política básica documentada. Implementación irregular. Dependencia de individuos específicos para aplicar y seguir la política. | G24: FALSE | J24: =+IF(G24=TRUE,'Guía de uso'!$Y$8,0) -> 0
A25: =+'Guía de uso'!$AA$9 -> Nivel 3 = Definido | B25: La política de seguridad está bien documentada y definida, siguiendo metodologías estándar con control y supervisión básicos. | D25: La política de seguridad está claramente documentada, siguiendo metodologías estándar, con un nivel básico de control y supervisión para asegurar su aplicación. | F25: Política bien definida y documentada. Uso de metodologías estándar. Control y supervisión básicos de la aplicación de la política. | G25: TRUE | J25: =+IF(G25=TRUE,'Guía de uso'!$Y$9,0) -> 3
A26: =+'Guía de uso'!$AA$10 -> Nivel 4 = Gestionado | B26: La política de seguridad está completamente integrada en los procesos, con supervisión regular y uso de métricas para evaluar su efectividad. | D26: La política de seguridad está integrada en los procesos organizacionales, con monitoreo continuo y uso de métricas y KPIs para asegurar su efectividad y mejora. | F26: Integración completa de la política en los procesos. Supervisión y control regulares. Uso de métricas y KPIs para evaluar la efectividad de la política. | G26: FALSE | J26: =+IF(G26=TRUE,'Guía de uso'!$Y$10,0) -> 0
A27: 2.3 Funciones, responsabilidades y autoridades de la organización: La alta dirección debe asegurarse de que las responsabilidades y autoridades para los roles relevantes en la seguridad de la información se asignen y comuniquen claramente dentro de la organización. Esto incluye asignar la responsabilidad y autoridad para garantizar que el SGSI cumpla con los requisitos de la norma ISO 27001 y para informar sobre el desempeño del SGSI a la alta dirección. | G27: =IF(COUNTIF(G29:G32,TRUE)>1,"SELECCIONE SOLAMENTE UN NIVEL","Marque la opción que describa mejor la situación actual del liderazgo") -> Marque la opción que describa mejor la situación actual del liderazgo
A28: Nivel | B28: Detalle | D28: Descripción | F28: Características
A29: =+'Guía de uso'!$AA$7 -> Nivel 1 = Inicial | B29: No se han definido ni documentado las funciones, responsabilidades y autoridades relacionadas con la seguridad de la información. | D29: Las actividades se llevan a cabo sin roles y responsabilidades claramente definidos, lo que provoca confusión y falta de responsabilidad en las acciones de seguridad. | F29: Ausencia de roles y responsabilidades definidos. Actividades sin dirección clara. Falta de responsabilidad en las acciones de seguridad. | G29: FALSE | J29: =+IF(G29=TRUE,'Guía de uso'!$Y$7,0) -> 0
A30: =+'Guía de uso'!$AA$8 -> Nivel 2 = Repetible | B30: Existen definiciones básicas de roles y responsabilidades, pero su implementación es inconsistente. | D30: Se han definido y documentado roles y responsabilidades básicas, pero su aplicación es irregular y depende de individuos específicos. | F30: Definición básica de roles y responsabilidades. Implementación irregular. Dependencia de individuos específicos para aplicar y seguir las definiciones. | G30: TRUE | J30: =+IF(G30=TRUE,'Guía de uso'!$Y$8,0) -> 2
A31: =+'Guía de uso'!$AA$9 -> Nivel 3 = Definido | B31: Las funciones, responsabilidades y autoridades están bien documentadas y definidas, siguiendo metodologías estándar con control básico. | D31: Las funciones y responsabilidades están claramente documentadas, siguiendo metodologías estándar, con un nivel básico de control y supervisión para asegurar su efectividad. | F31: Definición clara y documentada de roles y responsabilidades. Uso de metodologías estándar. Control y supervisión básica de la aplicación de las funciones. | G31: FALSE | J31: =+IF(G31=TRUE,'Guía de uso'!$Y$9,0) -> 0
A32: =+'Guía de uso'!$AA$10 -> Nivel 4 = Gestionado | B32: Las funciones, responsabilidades y autoridades están completamente integradas en los procesos, con supervisión regular y uso de métricas para evaluar su efectividad. | D32: Las funciones y responsabilidades están integradas en los procesos organizacionales, con monitoreo continuo y uso de métricas y KPIs para asegurar su efectividad y mejora continua. | F32: Integración completa de las funciones en los procesos. Supervisión y control regulares. Uso de métricas y KPIs para evaluar la efectividad de las funciones. | G32: FALSE | J32: =+IF(G32=TRUE,'Guía de uso'!$Y$10,0) -> 0
A34: CONCLUSIÓN Y/O OBSERVACIONES ADICIONALES

Sheet Check - Planificación
B1: Herramienta para medir el nivel actual de los Sistemas de gestión de seguridad de la información según ISO 27001:2022
A5: Entidad (o cliente): | C5: ID. | D5: Período de auditoría de: 1/01/2023 | E5: Hasta: 31/12/2023 | G5: Referencia
A6: Preparado por: | D6: Revisado por: | G6: XX-XX
A7: Supervisado por: | D7: Aprobado por:
A10: OBJETIVO
A11: Esta herramienta permite evaluar y asegurar el estado actual de la implementación, mantenimiento y mejora del sistema de gestión de la seguridad de la información (SGSI) según la norma ISO 27001:2022, y determinar si está integrado y aplicado de manera efectiva en la organización. Esto incluye verificar que la seguridad de la información está gestionada de forma sistemática, adaptada a las necesidades organizacionales, y en mejora continua.
A12: ALCANCE
A13: La planificación es un componente crítico del sistema de gestión de la seguridad de la información (SGSI) según la norma ISO 27001:2022. Un enfoque sistemático de la planificación asegura que los riesgos y oportunidades relacionados con la seguridad de la información sean identificados y gestionados adecuadamente. Esto permite a la organización establecer objetivos claros y formular estrategias para alcanzarlos, garantizando así la protección continua de la información.
A14: CHECKLIST ISO 27001 - PLANIFICACIÓN
A15: 3.1. Acciones para abordar riesgos y oportunidades: La organización debe planificar las acciones necesarias para abordar los riesgos y oportunidades que pueden afectar la capacidad del SGSI para lograr los resultados previstos. Esto incluye garantizar que el SGSI pueda alcanzar sus objetivos, prevenir o reducir efectos no deseados y fomentar la mejora continua. La planificación debe integrar estas acciones en los procesos del SGSI y evaluar su efectividad. | G15: =IF(COUNTIF(G17:G20,TRUE)>1,"SELECCIONE SOLAMENTE UN NIVEL","Marque la opción que describa mejor la situación actual del proceso de planificación") -> Marque la opción que describa mejor la situación actual del proceso de planificación
A16: Nivel | B16: Detalle | D16: Descripción | F16: Características
A17: =+'Guía de uso'!$AA$7 -> Nivel 1 = Inicial | B17: No se toman acciones formales para abordar riesgos y oportunidades. | D17: Las acciones relacionadas con riesgos y oportunidades son ad-hoc y no estructuradas, sin documentación formal ni seguimiento sistemático. | F17: Ausencia de acciones formales. Actividades reactivas y no estructuradas. Falta de documentación y seguimiento. | G17: FALSE | J17: =+IF(G17=TRUE,'Guía de uso'!$Y$7,0) -> 0
A18: =+'Guía de uso'!$AA$8 -> Nivel 2 = Repetible | B18: Existen esfuerzos básicos documentados para abordar riesgos y oportunidades, pero su implementación es inconsistente. | D18: Se han documentado acciones para abordar riesgos y oportunidades, pero la implementación depende de individuos específicos y no es sistemática. | F18: Documentación básica de acciones. Implementación irregular. Dependencia de individuos específicos. | G18: TRUE | J18: =+IF(G18=TRUE,'Guía de uso'!$Y$8,0) -> 2
A19: =+'Guía de uso'!$AA$9 -> Nivel 3 = Definido | B19: Las acciones para abordar riesgos y oportunidades están bien documentadas y siguen metodologías estándar con control básico. | D19: Las acciones están claramente documentadas, siguiendo metodologías estándar, con un nivel básico de control y supervisión para asegurar su efectividad. | F19: Documentación clara y definida de acciones. Uso de metodologías estándar. Control y supervisión básicos. | G19: FALSE | J19: =+IF(G19=TRUE,'Guía de uso'!$Y$9,0) -> 0
A20: =+'Guía de uso'!$AA$10 -> Nivel 4 = Gestionado | B20: Las acciones para abordar riesgos y oportunidades están completamente integradas en los procesos, con supervisión regular y métricas de evaluación. | D20: Las acciones están integradas en los procesos organizacionales, con monitoreo continuo y uso de métricas y KPIs para asegurar la efectividad y mejora. | F20: Integración completa en los procesos. Supervisión y control regulares. Uso de métricas y KPIs para evaluar la efectividad de las acciones. | G20: FALSE | J20: =+IF(G20=TRUE,'Guía de uso'!$Y$10,0) -> 0
A21: 3.2 Objetivos de Seguridad de la Información y planificación para alcanzarlos: La organización debe establecer objetivos de seguridad de la información en las funciones y niveles pertinentes. Estos objetivos deben ser coherentes con la política de seguridad de la información, medibles, monitoreados, comunicados y actualizados según corresponda. La planificación para alcanzar estos objetivos debe incluir la determinación de las acciones necesarias, los recursos requeridos, las responsabilidades asignadas, los plazos y los métodos para evaluar los resultados. | G21: =IF(COUNTIF(G23:G26,TRUE)>1,"SELECCIONE SOLAMENTE UN NIVEL","Marque la opción que describa mejor la situación actual del proceso de planificación") -> Marque la opción que describa mejor la situación actual del proceso de planificación
A22: Nivel | B22: Detalle | D22: Descripción | F22: Características
A23: =+'Guía de uso'!$AA$7 -> Nivel 1 = Inicial | B23: No se han establecido ni documentado objetivos de seguridad de la información. | D23: Las actividades de seguridad se realizan sin objetivos claros, lo que resulta en una falta de dirección y coherencia en las acciones de seguridad. | F23: Ausencia de objetivos formales. Actividades de seguridad sin dirección clara. Falta de coherencia en las acciones de seguridad. | G23: FALSE | J23: =+IF(G23=TRUE,'Guía de uso'!$Y$7,0) -> 0
A24: =+'Guía de uso'!$AA$8 -> Nivel 2 = Repetible | B24: Existen objetivos básicos de seguridad de la información, pero su implementación y seguimiento son inconsistentes. | D24: Se han establecido y documentado objetivos, pero la implementación y el seguimiento dependen de individuos específicos y no son sistemáticos. | F24: Objetivos básicos documentados. Implementación y seguimiento irregulares. Dependencia de individuos específicos. | G24: TRUE | J24: =+IF(G24=TRUE,'Guía de uso'!$Y$8,0) -> 2
A25: =+'Guía de uso'!$AA$9 -> Nivel 3 = Definido | B25: Los objetivos de seguridad están bien documentados y definidos, siguiendo metodologías estándar con control y supervisión básicos. | D25: Los objetivos de seguridad están claramente documentados y definidos, siguiendo metodologías estándar, con un nivel básico de control y supervisión para asegurar su efectividad. | F25: Objetivos bien definidos y documentados. Uso de metodologías estándar. Control y supervisión básicos. | G25: FALSE | J25: =+IF(G25=TRUE,'Guía de uso'!$Y$9,0) -> 0
A26: =+'Guía de uso'!$AA$10 -> Nivel 4 = Gestionado | B26: Los objetivos de seguridad están completamente integrados en los procesos, con supervisión regular y uso de métricas para evaluar su efectividad. | D26: Los objetivos de seguridad están integrados en los procesos organizacionales, con monitoreo continuo y uso de métricas y KPIs para asegurar la efectividad y mejora. | F26: Integración completa de los objetivos en los procesos. Supervisión y control regulares. Uso de métricas y KPIs para evaluar la efectividad de los objetivos. | G26: FALSE | J26: =+IF(G26=TRUE,'Guía de uso'!$Y$10,0) -> 0
A28: CONCLUSIÓN Y/O OBSERVACIONES ADICIONALES

Sheet Check - Soporte
B1: Herramienta para medir el nivel actual de los Sistemas de gestión de seguridad de la información según ISO 27001:2022
A5: Entidad (o cliente): | C5: ID. | D5: Período de auditoría de: 1/01/2023 | E5: Hasta: 31/12/2023 | G5: Referencia
A6: Preparado por: | D6: Revisado por: | G6: XX-XX
A7: Supervisado por: | D7: Aprobado por:
A10: OBJETIVO
A11: Esta herramienta permite evaluar y asegurar el estado actual de la implementación, mantenimiento y mejora del sistema de gestión de la seguridad de la información (SGSI) según la norma ISO 27001:2022, y determinar si está integrado y aplicado de manera efectiva en la organización. Esto incluye verificar que la seguridad de la información está gestionada de forma sistemática, adaptada a las necesidades organizacionales, y en mejora continua.
A12: ALCANCE
A13: El soporte es un pilar fundamental para la implementación y mantenimiento eficaz de un sistema de gestión de la seguridad de la información (SGSI) según la norma ISO 27001:2022. Este aspecto abarca todos los recursos necesarios, desde la competencia del personal hasta la gestión de la información documentada, asegurando que el SGSI funcione de manera eficiente y alcance sus objetivos de protección de la información.
A14: CHECKLIST ISO 27001 - SOPORTE
A15: 4.1 Recursos: Para que el SGSI sea efectivo, la organización debe determinar y proporcionar los recursos necesarios para su establecimiento, implementación, mantenimiento y mejora continua. Estos recursos incluyen personal, infraestructura, entorno de trabajo, recursos financieros y tecnológicos. | G15: =IF(COUNTIF(G17:G20,TRUE)>1,"SELECCIONE SOLAMENTE UN NIVEL","Marque la opción que describa mejor la situación actual del soporte ") -> Marque la opción que describa mejor la situación actual del soporte
A16: Nivel | B16: Detalle | D16: Descripción | F16: Características
A17: =+'Guía de uso'!$AA$7 -> Nivel 1 = Inicial | B17: No se asignan recursos específicos para la gestión de la seguridad de la información. | D17: Los recursos necesarios para la seguridad de la información no están definidos ni proporcionados, lo que resulta en una gestión ineficaz y reactiva. | F17: Falta de asignación de recursos. Actividades reactivas y no planificadas. | G17: FALSE | J17: =+IF(G17=TRUE,'Guía de uso'!$Y$7,0) -> 0
A18: =+'Guía de uso'!$AA$8 -> Nivel 2 = Repetible | B18: Se asignan recursos básicos, pero de manera inconsistente y dependiente de personas específicas. | D18: Hay esfuerzos por asignar recursos, pero estos son insuficientes y su asignación es irregular, dependiendo en gran medida de individuos específicos. | F18: Asignación básica e irregular de recursos. Dependencia de individuos específicos. | G18: FALSE | J18: =+IF(G18=TRUE,'Guía de uso'!$Y$8,0) -> 0
A19: =+'Guía de uso'!$AA$9 -> Nivel 3 = Definido | B19: Los recursos están bien definidos y asignados, siguiendo metodologías estándar con control básico. | D19: Los recursos necesarios para la seguridad de la información están claramente definidos y asignados, siguiendo metodologías estándar, con un nivel básico de control. | F19: Definición clara y asignación de recursos. Uso de metodologías estándar. Control y supervisión básicos de la asignación de recursos. | G19: TRUE | J19: =+IF(G19=TRUE,'Guía de uso'!$Y$9,0) -> 3
A20: =+'Guía de uso'!$AA$10 -> Nivel 4 = Gestionado | B20: Los recursos están completamente integrados en los procesos, con supervisión regular y uso de métricas para evaluar su suficiencia. | D20: La asignación de recursos está completamente integrada en los procesos organizacionales, con monitoreo continuo y uso de métricas y KPIs para evaluar su efectividad. | F20: Integración completa de la asignación de recursos en los procesos. Supervisión y control regulares. Uso de métricas y KPIs para evaluar la suficiencia de los recursos. | G20: FALSE | J20: =+IF(G20=TRUE,'Guía de uso'!$Y$10,0) -> 0
A21: 4.2. Competencia: La organización debe identificar la competencia necesaria para las personas que realizan trabajos bajo su control que afectan el desempeño de la seguridad de la información. Esto implica garantizar que estas personas sean competentes con base a una educación, formación o experiencia adecuada. Además, la organización debe tomar acciones para adquirir la competencia necesaria y evaluar la efectividad de estas acciones. | G21: =IF(COUNTIF(G23:G26,TRUE)>1,"SELECCIONE SOLAMENTE UN NIVEL","Marque la opción que describa mejor la situación actual del soporte ") -> Marque la opción que describa mejor la situación actual del soporte
A22: Nivel | B22: Detalle | D22: Descripción | F22: Características
A23: =+'Guía de uso'!$AA$7 -> Nivel 1 = Inicial | B23: No se evalúa ni se asegura la competencia del personal en materia de seguridad de la información. | D23: No existen procedimientos formales para evaluar y asegurar la competencia del personal, resultando en una falta de habilidades adecuadas para la seguridad. | F23: Ausencia de evaluación de competencias. Falta de habilidades adecuadas en seguridad de la información. | G23: FALSE | J23: =+IF(G23=TRUE,'Guía de uso'!$Y$7,0) -> 0
A24: =+'Guía de uso'!$AA$8 -> Nivel 2 = Repetible | B24: Se realizan esfuerzos básicos para evaluar la competencia, pero de manera inconsistente y dependiente de individuos específicos. | D24: Hay intentos por asegurar la competencia del personal, pero estos esfuerzos son irregulares y dependen de individuos específicos. | F24: Evaluación básica e irregular de competencias. Dependencia de individuos específicos. | G24: FALSE | J24: =+IF(G24=TRUE,'Guía de uso'!$Y$8,0) -> 0
A25: =+'Guía de uso'!$AA$9 -> Nivel 3 = Definido | B25: La competencia del personal está bien definida y evaluada, siguiendo metodologías estándar con control básico. | D25: Los requisitos de competencia están claramente definidos y se evalúan siguiendo metodologías estándar, con un nivel básico de control y supervisión. | F25: Definición clara y evaluación de competencias. Uso de metodologías estándar. Control y supervisión básicos de la competencia del personal. | G25: TRUE | J25: =+IF(G25=TRUE,'Guía de uso'!$Y$9,0) -> 3
A26: =+'Guía de uso'!$AA$10 -> Nivel 4 = Gestionado | B26: La competencia está completamente integrada en los procesos, con supervisión regular y uso de métricas para evaluar su efectividad. | D26: La competencia del personal está completamente integrada en los procesos organizacionales, con monitoreo continuo y uso de métricas y KPIs para asegurar la efectividad. | F26: Integración completa de la competencia en los procesos. Supervisión y control regulares. Uso de métricas y KPIs para evaluar la efectividad de la competencia. | G26: FALSE | J26: =+IF(G26=TRUE,'Guía de uso'!$Y$10,0) -> 0
A27: 4.3. Conciencia: El personal que realiza trabajos bajo el control de la organización debe ser consciente de la política de seguridad de la información, su contribución a la eficacia del SGSI y las implicaciones de no cumplir con los requisitos del SGSI. Asegurar la conciencia del personal es crucial para crear una cultura de seguridad de la información en toda la organización, donde cada individuo entiende su papel y responsabilidad en la protección de la información. | G27: =IF(COUNTIF(G29:G32,TRUE)>1,"SELECCIONE SOLAMENTE UN NIVEL","Marque la opción que describa mejor la situación actual del soporte ") -> Marque la opción que describa mejor la situación actual del soporte
A28: Nivel | B28: Detalle | D28: Descripción | F28: Características
A29: =+'Guía de uso'!$AA$7 -> Nivel 1 = Inicial | B29: No se realizan actividades formales para concienciar al personal sobre la seguridad de la información. | D29: Las actividades de concienciación son esporádicas y no están documentadas, resultando en una falta de entendimiento y compromiso del personal con la seguridad. | F29: Ausencia de actividades formales de concienciación. Falta de entendimiento y compromiso del personal. | G29: FALSE | J29: =+IF(G29=TRUE,'Guía de uso'!$Y$7,0) -> 0
A30: =+'Guía de uso'!$AA$8 -> Nivel 2 = Repetible | B30: Se realizan esfuerzos básicos de concienciación, pero de manera inconsistente y dependiente de individuos específicos. | D30: Hay intentos por concienciar al personal sobre la seguridad, pero estos esfuerzos son irregulares y dependen de individuos específicos. | F30: Esfuerzos básicos e irregulares de concienciación. Dependencia de individuos específicos. | G30: TRUE | J30: =+IF(G30=TRUE,'Guía de uso'!$Y$8,0) -> 2
A31: =+'Guía de uso'!$AA$9 -> Nivel 3 = Definido | B31: La concienciación sobre seguridad está bien documentada y definida, siguiendo metodologías estándar con control básico. | D31: Las actividades de concienciación están claramente documentadas y definidas, siguiendo metodologías estándar, con un nivel básico de control y supervisión. | F31: Documentación y definición claras de las actividades de concienciación. Uso de metodologías estándar. Control y supervisión básicos de la concienciación. | G31: FALSE | J31: =+IF(G31=TRUE,'Guía de uso'!$Y$9,0) -> 0
A32: =+'Guía de uso'!$AA$10 -> Nivel 4 = Gestionado | B32: La concienciación está completamente integrada en los procesos, con supervisión regular y uso de métricas para evaluar su efectividad. | D32: La concienciación sobre seguridad está completamente integrada en los procesos organizacionales, con monitoreo continuo y uso de métricas y KPIs para asegurar la efectividad. | F32: Integración completa de la concienciación en los procesos. Supervisión y control regulares. Uso de métricas y KPIs para evaluar la efectividad de la concienciación. | G32: FALSE | J32: =+IF(G32=TRUE,'Guía de uso'!$Y$10,0) -> 0
A33: 4.4. Comunicación: La organización debe determinar la necesidad de comunicaciones internas y externas relevantes para el SGSI. Esto incluye decidir sobre qué comunicar, cuándo comunicar, con quién comunicarse y cómo comunicarse. La comunicación efectiva asegura que todos los interesados, tanto internos como externos, estén informados sobre los aspectos relevantes de la seguridad de la información, facilitando la cooperación y la alineación de objetivos. | G33: =IF(COUNTIF(G35:G38,TRUE)>1,"SELECCIONE SOLAMENTE UN NIVEL","Marque la opción que describa mejor la situación actual del soporte ") -> Marque la opción que describa mejor la situación actual del soporte
A34: Nivel | B34: Detalle | D34: Descripción | F34: Características
A35: =+'Guía de uso'!$AA$7 -> Nivel 1 = Inicial | B35: No se establecen ni documentan procedimientos formales de comunicación sobre seguridad de la información. | D35: Las actividades de comunicación son ad-hoc y no están documentadas, lo que provoca una falta de coordinación y coherencia en la seguridad de la información. | F35: Ausencia de procedimientos formales de comunicación. Falta de coordinación y coherencia en las comunicaciones. | G35: FALSE | J35: =+IF(G35=TRUE,'Guía de uso'!$Y$7,0) -> 0
A36: =+'Guía de uso'!$AA$8 -> Nivel 2 = Repetible | B36: Existen procedimientos básicos de comunicación, pero su implementación es inconsistente y depende de individuos específicos. | D36: Se han establecido procedimientos para la comunicación, pero su implementación y seguimiento son irregulares y dependen de individuos específicos. | F36: Procedimientos básicos de comunicación. Implementación irregular. Dependencia de individuos específicos. | G36: FALSE | J36: =+IF(G36=TRUE,'Guía de uso'!$Y$8,0) -> 0
A37: =+'Guía de uso'!$AA$9 -> Nivel 3 = Definido | B37: Los procedimientos de comunicación están bien documentados y definidos, siguiendo metodologías estándar con control básico. | D37: Los procedimientos de comunicación están claramente documentados y definidos, siguiendo metodologías estándar, con un nivel básico de control y supervisión. | F37: Documentación y definición claras de los procedimientos de comunicación. Uso de metodologías estándar. Control y supervisión básicos de la comunicación. | G37: TRUE | J37: =+IF(G37=TRUE,'Guía de uso'!$Y$9,0) -> 3
A38: =+'Guía de uso'!$AA$10 -> Nivel 4 = Gestionado | B38: La comunicación está completamente integrada en los procesos, con supervisión regular y uso de métricas para evaluar su efectividad. | D38: La comunicación sobre seguridad está completamente integrada en los procesos organizacionales, con monitoreo continuo y uso de métricas y KPIs para asegurar la efectividad. | F38: Integración completa de la comunicación en los procesos. Supervisión y control regulares. Uso de métricas y KPIs para evaluar la efectividad de la comunicación. | G38: FALSE | J38: =+IF(G38=TRUE,'Guía de uso'!$Y$10,0) -> 0
A39: 4.5. Información documentada: La gestión de la información documentada es un componente clave del SGSI. La organización debe garantizar que se mantenga la información documentada requerida por la norma ISO 27001 y cualquier información adicional que la organización considere necesaria para la eficacia del SGSI. Esto incluye la creación y actualización de documentos, asegurando su identificación, formato y revisión adecuados. | G39: =IF(COUNTIF(G41:G44,TRUE)>1,"SELECCIONE SOLAMENTE UN NIVEL","Marque la opción que describa mejor la situación actual del soporte ") -> Marque la opción que describa mejor la situación actual del soporte
A40: Nivel | B40: Detalle | D40: Descripción | F40: Características
A41: =+'Guía de uso'!$AA$7 -> Nivel 1 = Inicial | B41: No se gestiona ni se controla formalmente la información documentada. | D41: Las actividades de documentación son esporádicas y no están formalizadas, resultando en una falta de control y coherencia en la gestión de la información. | F41: Ausencia de gestión formal de la documentación. Falta de control y coherencia en la documentación. | G41: FALSE | J41: =+IF(G41=TRUE,'Guía de uso'!$Y$7,0) -> 0
A42: =+'Guía de uso'!$AA$8 -> Nivel 2 = Repetible | B42: Existen esfuerzos básicos para gestionar la información documentada, pero de manera inconsistente y dependiente de individuos específicos. | D42: Se han establecido procedimientos básicos para la gestión de la información, pero su implementación es irregular y depende de individuos específicos. | F42: Esfuerzos básicos e irregulares de gestión de la información. Dependencia de individuos específicos. | G42: TRUE | J42: =+IF(G42=TRUE,'Guía de uso'!$Y$8,0) -> 2
A43: =+'Guía de uso'!$AA$9 -> Nivel 3 = Definido | B43: Los procedimientos para gestionar la información están bien documentados y definidos, siguiendo metodologías estándar con control básico. | D43: Los procedimientos para gestionar la información están claramente documentados y definidos, siguiendo metodologías estándar, con un nivel básico de control y supervisión. | F43: Documentación y definición claras de los procedimientos de gestión. Uso de metodologías estándar. Control y supervisión básicos de la documentación. | G43: FALSE | J43: =+IF(G43=TRUE,'Guía de uso'!$Y$9,0) -> 0
A44: =+'Guía de uso'!$AA$10 -> Nivel 4 = Gestionado | B44: La gestión de la información está completamente integrada en los procesos, con supervisión regular y uso de métricas para evaluar su efectividad. | D44: La gestión de la información está completamente integrada en los procesos organizacionales, con monitoreo continuo y uso de métricas y KPIs para asegurar la efectividad. | F44: Integración completa de la gestión de la información en los procesos. Supervisión y control regulares. Uso de métricas y KPIs para evaluar la efectividad de la gestión de la información. | G44: FALSE | J44: =+IF(G44=TRUE,'Guía de uso'!$Y$10,0) -> 0
A46: CONCLUSIÓN Y/O OBSERVACIONES ADICIONALES

Sheet Check - Operación
B1: Herramienta para medir el nivel actual de los Sistemas de gestión de seguridad de la información según ISO 27001:2022
A5: Entidad (o cliente): | C5: ID. | D5: Período de auditoría de: 1/01/2023 | E5: Hasta: 31/12/2023 | G5: Referencia
A6: Preparado por: | D6: Revisado por: | G6: XX-XX
A7: Supervisado por: | D7: Aprobado por:
A10: OBJETIVO
A11: Esta herramienta permite evaluar y asegurar el estado actual de la implementación, mantenimiento y mejora del sistema de gestión de la seguridad de la información (SGSI) según la norma ISO 27001:2022, y determinar si está integrado y aplicado de manera efectiva en la organización. Esto incluye verificar que la seguridad de la información está gestionada de forma sistemática, adaptada a las necesidades organizacionales, y en mejora continua.
A12: ALCANCE
A13: La operación es un aspecto crucial en la implementación y mantenimiento de un sistema de gestión de la seguridad de la información (SGSI) conforme a la norma ISO 27001:2022. Este aspecto se enfoca en la planificación, ejecución y control de los procesos necesarios para asegurar que se cumplan los requisitos de seguridad de la información y que las acciones planificadas se implementen de manera efectiva.
A14: CHECKLIST ISO 27001 - OPERACIÓN
A15: 5.1 Planificación y control operativo: Para cumplir con los requisitos del SGSI y ejecutar las acciones determinadas, la organización debe planificar, implementar y controlar los procesos necesarios. Esto implica establecer criterios para los procesos y asegurar que estos se lleven a cabo de acuerdo con los criterios establecidos. Además, la organización debe gestionar los cambios planificados y revisar las consecuencias de los cambios no deseados, tomando medidas para mitigar cualquier efecto adverso. | G15: =IF(COUNTIF(G17:G20,TRUE)>1,"SELECCIONE SOLAMENTE UN NIVEL","Marque la opción que describa mejor la situación actual de la operación del SGSI ") -> Marque la opción que describa mejor la situación actual de la operación del SGSI
A16: Nivel | B16: Detalle | D16: Descripción | F16: Características
A17: =+'Guía de uso'!$AA$7 -> Nivel 1 = Inicial | B17: No se planifican ni se controlan formalmente las operaciones relacionadas con la seguridad de la información. | D17: Las actividades operativas relacionadas con la seguridad son ad-hoc y no están documentadas, lo que resulta en una falta de coordinación y control. | F17: Falta de planificación y control formal. Actividades reactivas y no documentadas. | G17: FALSE | J17: =+IF(G17=TRUE,'Guía de uso'!$Y$7,0) -> 0
A18: =+'Guía de uso'!$AA$8 -> Nivel 2 = Repetible | B18: Se realizan esfuerzos básicos para planificar y controlar las operaciones, pero de manera inconsistente y dependiente de individuos específicos. | D18: Se ha comenzado a planificar y controlar las operaciones, pero la implementación es irregular y depende en gran medida de individuos específicos. | F18: Planificación básica e irregular. Dependencia de individuos específicos para el control. | G18: TRUE | J18: =+IF(G18=TRUE,'Guía de uso'!$Y$8,0) -> 2
A19: =+'Guía de uso'!$AA$9 -> Nivel 3 = Definido | B19: La planificación y el control operativo están bien documentados y definidos, siguiendo metodologías estándar con control básico. | D19: Las operaciones están claramente planificadas y controladas, siguiendo metodologías estándar, con un nivel básico de supervisión y control para asegurar su efectividad. | F19: Documentación clara y definición de procedimientos operativos. Uso de metodologías estándar. Control y supervisión básicos. | G19: FALSE | J19: =+IF(G19=TRUE,'Guía de uso'!$Y$9,0) -> 0
A20: =+'Guía de uso'!$AA$10 -> Nivel 4 = Gestionado | B20: La planificación y el control operativo están completamente integrados en los procesos, con supervisión regular y uso de métricas para evaluar su efectividad. | D20: La planificación y el control operativo están integrados en los procesos organizacionales, con monitoreo continuo y uso de métricas y KPIs para asegurar la efectividad y mejora. | F20: Integración completa de la planificación y el control operativo en los procesos. Supervisión y control regulares. Uso de métricas y KPIs para evaluar la efectividad operativa. | G20: FALSE | J20: =+IF(G20=TRUE,'Guía de uso'!$Y$10,0) -> 0
A21: 5.2 Evaluación de riesgos de Seguridad de la Información: La organización debe realizar evaluaciones de riesgos de seguridad de la información a intervalos planificados o cuando se proponen o ocurren cambios significativos. Estas evaluaciones deben basarse en los criterios establecidos y documentarse adecuadamente. La evaluación regular de los riesgos permite a la organización identificar y mitigar nuevas amenazas de manera oportuna, manteniendo la integridad, confidencialidad y disponibilidad de la información. | G21: =IF(COUNTIF(G23:G26,TRUE)>1,"SELECCIONE SOLAMENTE UN NIVEL","Marque la opción que describa mejor la situación actual de la operación del SGSI ") -> Marque la opción que describa mejor la situación actual de la operación del SGSI
A22: Nivel | B22: Detalle | D22: Descripción | F22: Características
A23: =+'Guía de uso'!$AA$7 -> Nivel 1 = Inicial | B23: No se realizan evaluaciones formales de riesgos de seguridad de la información. | D23: Las evaluaciones de riesgos son esporádicas y no están documentadas, lo que resulta en una falta de identificación y evaluación sistemática de los riesgos. | F23: Ausencia de evaluaciones formales. Evaluaciones esporádicas y no documentadas. Falta de identificación sistemática de riesgos. | G23: FALSE | J23: =+IF(G23=TRUE,'Guía de uso'!$Y$7,0) -> 0
A24: =+'Guía de uso'!$AA$8 -> Nivel 2 = Repetible | B24: Se realizan esfuerzos básicos para evaluar los riesgos, pero de manera inconsistente y dependiente de individuos específicos. | D24: Se han comenzado a evaluar los riesgos, pero la implementación es irregular y depende de individuos específicos para su efectividad. | F24: Evaluación básica e irregular de riesgos. Dependencia de individuos específicos para la evaluación. | G24: TRUE | J24: =+IF(G24=TRUE,'Guía de uso'!$Y$8,0) -> 2
A25: =+'Guía de uso'!$AA$9 -> Nivel 3 = Definido | B25: Los procesos de evaluación de riesgos están bien documentados y definidos, siguiendo metodologías estándar con control básico. | D25: Los procesos de evaluación de riesgos están claramente documentados y definidos, siguiendo metodologías estándar, con un nivel básico de control y supervisión. | F25: Procesos bien documentados y definidos. Uso de metodologías estándar. Control y supervisión básicos. | G25: FALSE | J25: =+IF(G25=TRUE,'Guía de uso'!$Y$9,0) -> 0
A26: =+'Guía de uso'!$AA$10 -> Nivel 4 = Gestionado | B26: La evaluación de riesgos está completamente integrada en los procesos, con supervisión regular y uso de métricas para evaluar su efectividad. | D26: La evaluación de riesgos está integrada en los procesos organizacionales, con monitoreo continuo y uso de métricas y KPIs para asegurar la efectividad y mejora. | F26: Integración completa en los procesos. Supervisión y control regulares. Uso de métricas y KPIs para evaluar la efectividad de la evaluación de riesgos. | G26: FALSE | J26: =+IF(G26=TRUE,'Guía de uso'!$Y$10,0) -> 0
A27: 5.3 Tratamiento de riesgos de Seguridad de la Información: Implementar el plan de tratamiento de riesgos es fundamental para gestionar eficazmente los riesgos identificados. La organización debe asegurarse de que las acciones de tratamiento de riesgos se lleven a cabo y que se conserven registros documentados de los resultados. Este proceso implica seleccionar las medidas de control adecuadas para mitigar los riesgos y asegurar que estas se implementen de manera efectiva. | G27: =IF(COUNTIF(G29:G32,TRUE)>1,"SELECCIONE SOLAMENTE UN NIVEL","Marque la opción que describa mejor la situación actual de la operación del SGSI ") -> Marque la opción que describa mejor la situación actual de la operación del SGSI
A28: Nivel | B28: Detalle | D28: Descripción | F28: Características
A29: =+'Guía de uso'!$AA$7 -> Nivel 1 = Inicial | B29: No se toman acciones formales para el tratamiento de riesgos de seguridad de la información. | D29: Las acciones relacionadas con el tratamiento de riesgos son ad-hoc y no están documentadas, resultando en una falta de mitigación sistemática de los riesgos. | F29: Ausencia de acciones formales. Actividades reactivas y no documentadas. Falta de proceso sistemático para mitigar riesgos. | G29: FALSE | J29: =+IF(G29=TRUE,'Guía de uso'!$Y$7,0) -> 0
A30: =+'Guía de uso'!$AA$8 -> Nivel 2 = Repetible | B30: Se realizan esfuerzos básicos para tratar los riesgos, pero de manera inconsistente y dependiente de individuos específicos. | D30: Se han documentado acciones para el tratamiento de riesgos, pero la implementación es irregular y depende de individuos específicos para su efectividad. | F30: Tratamiento básico e irregular de riesgos. Dependencia de individuos específicos para la mitigación. | G30: TRUE | J30: =+IF(G30=TRUE,'Guía de uso'!$Y$8,0) -> 2
A31: =+'Guía de uso'!$AA$9 -> Nivel 3 = Definido | B31: Los procesos de tratamiento de riesgos están bien documentados y definidos, siguiendo metodologías estándar con control básico. | D31: Los procesos de tratamiento de riesgos están claramente documentados y definidos, siguiendo metodologías estándar, con un nivel básico de control y supervisión. | F31: Procesos bien documentados y definidos. Uso de metodologías estándar. Control y supervisión básicos. | G31: FALSE | J31: =+IF(G31=TRUE,'Guía de uso'!$Y$9,0) -> 0
A32: =+'Guía de uso'!$AA$10 -> Nivel 4 = Gestionado | B32: El tratamiento de riesgos está completamente integrado en los procesos, con supervisión regular y uso de métricas para evaluar su efectividad. | D32: El tratamiento de riesgos está integrado en los procesos organizacionales, con monitoreo continuo y uso de métricas y KPIs para asegurar la efectividad y mejora. | F32: Integración completa en los procesos. Supervisión y control regulares. Uso de métricas y KPIs para evaluar la efectividad del tratamiento de riesgos. | G32: FALSE | J32: =+IF(G32=TRUE,'Guía de uso'!$Y$10,0) -> 0
A34: CONCLUSIÓN Y/O OBSERVACIONES ADICIONALES

Sheet Check - Evaluación
B1: Herramienta para medir el nivel actual de los Sistemas de gestión de seguridad de la información según ISO 27001:2022
A5: Entidad (o cliente): | C5: ID. | D5: Período de auditoría de: 1/01/2023 | E5: Hasta: 31/12/2023 | G5: Referencia
A6: Preparado por: | D6: Revisado por: | G6: XX-XX
A7: Supervisado por: | D7: Aprobado por:
A10: OBJETIVO
A11: Esta herramienta permite evaluar y asegurar el estado actual de la implementación, mantenimiento y mejora del sistema de gestión de la seguridad de la información (SGSI) según la norma ISO 27001:2022, y determinar si está integrado y aplicado de manera efectiva en la organización. Esto incluye verificar que la seguridad de la información está gestionada de forma sistemática, adaptada a las necesidades organizacionales, y en mejora continua.
A12: ALCANCE
A13: La evaluación del desempeño es un aspecto esencial para garantizar la eficacia continua de un sistema de gestión de la seguridad de la información (SGSI) según la norma ISO 27001:2022. Este aspecto se centra en el monitoreo, la medición, el análisis y la evaluación de los procesos y controles de seguridad de la información para asegurar que cumplan con los objetivos establecidos y se mantengan alineados con las necesidades y expectativas de la organización y sus partes interesadas.
A14: CHECKLIST ISO 27001 - EVALUACIÓN DEL DESEMPEÑO
A15: 6.1 Seguimiento, medición, análisis y evaluación: Para evaluar eficazmente el desempeño del SGSI, la organización debe determinar qué debe monitorearse y medirse, incluidos los procesos y controles de seguridad de la información. Esto implica definir métodos válidos y consistentes para el seguimiento y la medición, así como determinar cuándo y quién debe realizar estas actividades. | G15: =IF(COUNTIF(G17:G20,TRUE)>1,"SELECCIONE SOLAMENTE UN NIVEL","Marque la opción que describa mejor la situación actual del proceso de evaluación del desempeño") -> Marque la opción que describa mejor la situación actual del proceso de evaluación del desempeño
A16: Nivel | B16: Detalle | D16: Descripción | F16: Características
A17: =+'Guía de uso'!$AA$7 -> Nivel 1 = Inicial | B17: No se realizan actividades formales de seguimiento, medición, análisis y evaluación. | D17: Las actividades son ad-hoc y no están documentadas, lo que resulta en una falta de datos precisos para la toma de decisiones sobre la seguridad de la información. | F17: Ausencia de actividades formales. Actividades reactivas y no documentadas. Falta de datos precisos. | G17: FALSE | J17: =+IF(G17=TRUE,'Guía de uso'!$Y$7,0) -> 0
A18: =+'Guía de uso'!$AA$8 -> Nivel 2 = Repetible | B18: Se realizan esfuerzos básicos, pero de manera inconsistente y dependiente de individuos específicos. | D18: Existen esfuerzos para medir y evaluar, pero son irregulares y dependen de individuos específicos, lo que afecta la consistencia y precisión de los datos. | F18: Esfuerzos básicos e irregulares. Dependencia de individuos específicos. | G18: FALSE | J18: =+IF(G18=TRUE,'Guía de uso'!$Y$8,0) -> 0
A19: =+'Guía de uso'!$AA$9 -> Nivel 3 = Definido | B19: Las actividades de seguimiento, medición, análisis y evaluación están bien documentadas y definidas, siguiendo metodologías estándar con control básico. | D19: Las actividades están claramente documentadas, siguiendo metodologías estándar, con un nivel básico de control y supervisión para asegurar la exactitud y utilidad de los datos. | F19: Documentación clara y definición de procedimientos. Uso de metodologías estándar. Control y supervisión básicos. | G19: TRUE | J19: =+IF(G19=TRUE,'Guía de uso'!$Y$9,0) -> 3
A20: =+'Guía de uso'!$AA$10 -> Nivel 4 = Gestionado | B20: Estas actividades están completamente integradas en los procesos, con supervisión regular y uso de métricas para evaluar su efectividad. | D20: Las actividades están integradas en los procesos organizacionales, con monitoreo continuo y uso de métricas y KPIs para asegurar la efectividad y mejora. | F20: Integración completa en los procesos. Supervisión y control regulares. Uso de métricas y KPIs para evaluar la efectividad de las actividades. | G20: FALSE | J20: =+IF(G20=TRUE,'Guía de uso'!$Y$10,0) -> 0
A21: 6.2 Auditoría Interna: Las auditorías internas son fundamentales para proporcionar información sobre la conformidad del SGSI con los requisitos internos y los de la norma ISO 27001. La organización debe realizar auditorías internas a intervalos planificados, asegurándose de que estas auditorías sean objetivas e imparciales. Un programa de auditoría interna bien establecido incluye la definición de criterios y alcance, la selección de auditores y la planificación de las auditorías. Los resultados de las auditorías deben ser documentados y comunicados a la dirección pertinente para facilitar la toma de decisiones informadas y la implementación de acciones correctivas cuando sea necesario. | G21: =IF(COUNTIF(G23:G26,TRUE)>1,"SELECCIONE SOLAMENTE UN NIVEL","Marque la opción que describa mejor la situación actual del proceso de evaluación del desempeño") -> Marque la opción que describa mejor la situación actual del proceso de evaluación del desempeño
A22: Nivel | B22: Detalle | D22: Descripción | F22: Características
A23: =+'Guía de uso'!$AA$7 -> Nivel 1 = Inicial | B23: No se realizan auditorías internas formales para evaluar la seguridad de la información. | D23: Las auditorías internas son esporádicas y no están documentadas, lo que provoca una falta de evaluación sistemática y formal de la efectividad del SGSI. | F23: Ausencia de auditorías internas formales. Evaluaciones esporádicas y no documentadas. Falta de evaluación sistemática. | G23: FALSE | J23: =+IF(G23=TRUE,'Guía de uso'!$Y$7,0) -> 0
A24: =+'Guía de uso'!$AA$8 -> Nivel 2 = Repetible | B24: Se realizan auditorías internas básicas, pero de manera inconsistente y dependiente de individuos específicos. | D24: Existen esfuerzos para realizar auditorías internas, pero son irregulares y dependen de individuos específicos, lo que afecta la consistencia de las evaluaciones. | F24: Auditorías internas básicas e irregulares. Dependencia de individuos específicos para las auditorías. | G24: TRUE | J24: =+IF(G24=TRUE,'Guía de uso'!$Y$8,0) -> 2
A25: =+'Guía de uso'!$AA$9 -> Nivel 3 = Definido | B25: Las auditorías internas están bien documentadas y definidas, siguiendo metodologías estándar con control básico. | D25: Las auditorías internas están claramente documentadas, siguiendo metodologías estándar, con un nivel básico de control y supervisión para asegurar su efectividad. | F25: Documentación clara y definición de procedimientos. Uso de metodologías estándar. Control y supervisión básicos. | G25: FALSE | J25: =+IF(G25=TRUE,'Guía de uso'!$Y$9,0) -> 0
A26: =+'Guía de uso'!$AA$10 -> Nivel 4 = Gestionado | B26: Las auditorías internas están completamente integradas en los procesos, con supervisión regular y uso de métricas para evaluar su efectividad. | D26: Las auditorías internas están integradas en los procesos organizacionales, con monitoreo continuo y uso de métricas y KPIs para asegurar la efectividad y mejora. | F26: Integración completa en los procesos. Supervisión y control regulares. Uso de métricas y KPIs para evaluar la efectividad de las auditorías. | G26: FALSE | J26: =+IF(G26=TRUE,'Guía de uso'!$Y$10,0) -> 0
A27: 6.3 Revisión por la Dirección: La revisión por la dirección es un proceso clave para asegurar la idoneidad, adecuación y eficacia continuas del SGSI. La alta dirección debe revisar el SGSI a intervalos planificados, considerando diversas entradas, como el estado de las acciones de revisiones anteriores, cambios en el contexto interno y externo, retroalimentación sobre el desempeño de la seguridad de la información y resultados de auditorías. Los resultados de esta revisión deben incluir decisiones sobre oportunidades de mejora continua y cualquier necesidad de cambios en el SGSI. | G27: =IF(COUNTIF(G29:G32,TRUE)>1,"SELECCIONE SOLAMENTE UN NIVEL","Marque la opción que describa mejor la situación actual del proceso de evaluación del desempeño") -> Marque la opción que describa mejor la situación actual del proceso de evaluación del desempeño
A28: Nivel | B28: Detalle | D28: Descripción | F28: Características
A29: =+'Guía de uso'!$AA$7 -> Nivel 1 = Inicial | B29: La alta dirección no realiza revisiones formales del SGSI. | D29: Las revisiones son esporádicas y no están documentadas, lo que resulta en una falta de evaluación sistemática de la idoneidad, adecuación y efectividad del SGSI. | F29: Ausencia de revisiones formales por la dirección. Revisiones esporádicas y no documentadas. Falta de evaluación sistemática. | G29: FALSE | J29: =+IF(G29=TRUE,'Guía de uso'!$Y$7,0) -> 0
A30: =+'Guía de uso'!$AA$8 -> Nivel 2 = Repetible | B30: Se realizan revisiones básicas del SGSI por la alta dirección, pero de manera inconsistente y dependiente de individuos específicos. | D30: Existen esfuerzos para revisar el SGSI, pero son irregulares y dependen de individuos específicos, lo que afecta la consistencia y utilidad de las revisiones. | F30: Revisiones básicas e irregulares del SGSI. Dependencia de individuos específicos para las revisiones. | G30: TRUE | J30: =+IF(G30=TRUE,'Guía de uso'!$Y$8,0) -> 2
A31: =+'Guía de uso'!$AA$9 -> Nivel 3 = Definido | B31: Las revisiones del SGSI por la dirección están bien documentadas y definidas, siguiendo metodologías estándar con control básico. | D31: Las revisiones están claramente documentadas, siguiendo metodologías estándar, con un nivel básico de control y supervisión para asegurar su efectividad. | F31: Documentación clara y definición de procedimientos. Uso de metodologías estándar. Control y supervisión básicos. | G31: FALSE | J31: =+IF(G31=TRUE,'Guía de uso'!$Y$9,0) -> 0
A32: =+'Guía de uso'!$AA$10 -> Nivel 4 = Gestionado | B32: Las revisiones del SGSI por la dirección están completamente integradas en los procesos, con supervisión regular y uso de métricas para evaluar su efectividad. | D32: Las revisiones del SGSI están integradas en los procesos de la alta dirección, con monitoreo continuo y uso de métricas y KPIs para asegurar la efectividad y mejora. | F32: Integración completa en los procesos de la alta dirección. Supervisión y control regulares. Uso de métricas y KPIs para evaluar la efectividad de las revisiones. | G32: FALSE | J32: =+IF(G32=TRUE,'Guía de uso'!$Y$10,0) -> 0
A34: CONCLUSIÓN Y/O OBSERVACIONES ADICIONALES

Sheet Check - Mejora
B1: Herramienta para medir el nivel actual de los Sistemas de gestión de seguridad de la información según ISO 27001:2022
A5: Entidad (o cliente): | C5: ID. | D5: Período de auditoría de: 1/01/2023 | E5: Hasta: 31/12/2023 | G5: Referencia
A6: Preparado por: | D6: Revisado por: | G6: XX-XX
A7: Supervisado por: | D7: Aprobado por:
A10: OBJETIVO
A11: Esta herramienta permite evaluar y asegurar el estado actual de la implementación, mantenimiento y mejora del sistema de gestión de la seguridad de la información (SGSI) según la norma ISO 27001:2022, y determinar si está integrado y aplicado de manera efectiva en la organización. Esto incluye verificar que la seguridad de la información está gestionada de forma sistemática, adaptada a las necesidades organizacionales, y en mejora continua.
A12: ALCANCE
A13: El aspecto de mejora es fundamental para mantener y aumentar la eficacia de un sistema de gestión de la seguridad de la información (SGSI) conforme a la norma ISO 27001:2022. La mejora continua asegura que el SGSI evolucione con el tiempo, adaptándose a nuevos desafíos y oportunidades, y alineándose constantemente con los objetivos estratégicos de la organización. Este enfoque proactivo permite a la organización responder eficazmente a incidentes de seguridad, prevenir recurrencias y fomentar una cultura de mejora constante.
A14: CHECKLIST ISO 27001 - MEJORA
A15: 7.1 Mejora continua: La organización debe comprometerse a mejorar continuamente la idoneidad, adecuación y eficacia del SGSI. Esto implica un enfoque sistemático para identificar oportunidades de mejora en todos los aspectos del SGSI, desde los procesos y controles hasta la cultura organizacional. La mejora continua no solo abarca la corrección de problemas identificados, sino también la búsqueda de maneras innovadoras para optimizar la seguridad de la información. | G15: =IF(COUNTIF(G17:G20,TRUE)>1,"SELECCIONE SOLAMENTE UN NIVEL","Marque la opción que describa mejor la situación actual del proceso de mejora") -> Marque la opción que describa mejor la situación actual del proceso de mejora
A16: Nivel | B16: Detalle | D16: Descripción | F16: Características
A17: =+'Guía de uso'!$AA$7 -> Nivel 1 = Inicial | B17: No se realizan actividades formales de mejora continua en la seguridad de la información. | D17: Las actividades de mejora son esporádicas y no documentadas, lo que resulta en una falta de progreso sistemático en la efectividad del SGSI. | F17: Ausencia de actividades formales de mejora. Mejora esporádica y no documentada. | G17: FALSE | J17: =+IF(G17=TRUE,'Guía de uso'!$Y$7,0) -> 0
A18: =+'Guía de uso'!$AA$8 -> Nivel 2 = Repetible | B18: Se realizan esfuerzos básicos para la mejora continua, pero de manera inconsistente y dependiente de individuos específicos. | D18: Existen esfuerzos para identificar y realizar mejoras, pero son irregulares y dependen de individuos específicos, afectando la consistencia del progreso. | F18: Esfuerzos básicos e irregulares de mejora. Dependencia de individuos específicos. | G18: TRUE | J18: =+IF(G18=TRUE,'Guía de uso'!$Y$8,0) -> 2
A19: =+'Guía de uso'!$AA$9 -> Nivel 3 = Definido | B19: Las actividades de mejora continua están bien documentadas y definidas, siguiendo metodologías estándar con control básico. | D19: Las actividades de mejora están claramente documentadas, siguiendo metodologías estándar, con un nivel básico de control y supervisión para asegurar su efectividad. | F19: Documentación clara y definición de procedimientos. Uso de metodologías estándar. Control y supervisión básicos. | G19: FALSE | J19: =+IF(G19=TRUE,'Guía de uso'!$Y$9,0) -> 0
A20: =+'Guía de uso'!$AA$10 -> Nivel 4 = Gestionado | B20: Las actividades de mejora continua están completamente integradas en los procesos, con supervisión regular y uso de métricas para evaluar su efectividad. | D20: Las actividades de mejora están integradas en los procesos organizacionales, con monitoreo continuo y uso de métricas y KPIs para asegurar la efectividad y mejora. | F20: Integración completa en los procesos. Supervisión y control regulares. Uso de métricas y KPIs para evaluar la efectividad de las mejoras. | G20: FALSE | J20: =+IF(G20=TRUE,'Guía de uso'!$Y$10,0) -> 0
A21: 7.2 No conformidad y acción correctiva: Cuando ocurre una no conformidad, la organización debe reaccionar de manera adecuada y tomar medidas para controlar y corregir la situación. Esto incluye evaluar la necesidad de acciones para eliminar las causas de la no conformidad y prevenir su recurrencia, tanto en el mismo lugar como en otros posibles puntos de falla. | G21: =IF(COUNTIF(G23:G26,TRUE)>1,"SELECCIONE SOLAMENTE UN NIVEL","Marque la opción que describa mejor la situación actual del proceso de mejora") -> Marque la opción que describa mejor la situación actual del proceso de mejora
A22: Nivel | B22: Detalle | D22: Descripción | F22: Características
A23: =+'Guía de uso'!$AA$7 -> Nivel 1 = Inicial | B23: No se gestionan formalmente las no conformidades ni se toman acciones correctivas. | D23: Las actividades relacionadas con la gestión de no conformidades y acciones correctivas son ad-hoc y no documentadas, resultando en una falta de resolución sistemática. | F23: Ausencia de gestión formal de no conformidades. Actividades reactivas y no documentadas. Falta de resolución sistemática. | G23: FALSE | J23: =+IF(G23=TRUE,'Guía de uso'!$Y$7,0) -> 0
A24: =+'Guía de uso'!$AA$8 -> Nivel 2 = Repetible | B24: Se realizan esfuerzos básicos para gestionar no conformidades y tomar acciones correctivas, pero de manera inconsistente y dependiente de individuos específicos. | D24: Existen esfuerzos para gestionar no conformidades y tomar acciones correctivas, pero son irregulares y dependen de individuos específicos, afectando la consistencia de la resolución. | F24: Gestión básica e irregular de no conformidades. Dependencia de individuos específicos para la resolución. | G24: TRUE | J24: =+IF(G24=TRUE,'Guía de uso'!$Y$8,0) -> 2
A25: =+'Guía de uso'!$AA$9 -> Nivel 3 = Definido | B25: Los procesos de gestión de no conformidades y acciones correctivas están bien documentados y definidos, siguiendo metodologías estándar con control básico. | D25: Los procesos están claramente documentados, siguiendo metodologías estándar, con un nivel básico de control y supervisión para asegurar su efectividad. | F25: Documentación clara y definición de procedimientos. Uso de metodologías estándar. Control y supervisión básicos. | G25: FALSE | J25: =+IF(G25=TRUE,'Guía de uso'!$Y$9,0) -> 0
A26: =+'Guía de uso'!$AA$10 -> Nivel 4 = Gestionado | B26: Los procesos de gestión de no conformidades y acciones correctivas están completamente integrados en los procesos, con supervisión regular y uso de métricas para evaluar su efectividad. | D26: Los procesos están integrados en los procesos organizacionales, con monitoreo continuo y uso de métricas y KPIs para asegurar la efectividad y mejora. | F26: Integración completa en los procesos. Supervisión y control regulares. Uso de métricas y KPIs para evaluar la efectividad de las acciones correctivas. | G26: FALSE | J26: =+IF(G26=TRUE,'Guía de uso'!$Y$10,0) -> 0
A28: CONCLUSIÓN Y/O OBSERVACIONES ADICIONALES

Sheet Recomendaciones
B2: RECOMENDACIONES PARA ALCANZAR EL SIGUIENTE NIVEL DE MADUREZ
A5: Entidad (o cliente): | C5: ID. | D5: Período de auditoría de: 1/01/2023 | F5: Referencia
A6: Preparado por: | D6: Revisado por: | F6: XX-XX
A7: Supervisado por: | D7: Aprobado por:
D8: =+'Guía de uso'!B21 -> Inicial | E8: =+'Guía de uso'!B22 -> Repetible | F8: =+'Guía de uso'!B23 -> Definido | G8: =+'Guía de uso'!B24 -> Gestionado
A9: RECOMENDACIONES DE ACCIONES QUE PERMITEN ALCANZAR EL SIGUIENTE NIVEL DE MADUREZ
D11: NIVELES DE MADUREZ
A12: PRINCIPIOS / ENFOQUE | D12: =+'Guía de uso'!$AA$7 -> Nivel 1 = Inicial | E12: =+'Guía de uso'!$AA$8 -> Nivel 2 = Repetible | F12: =+'Guía de uso'!$AA$9 -> Nivel 3 = Definido | G12: =+'Guía de uso'!$AA$10 -> Nivel 4 = Gestionado
A13: ISO 31000
A14: 1. | B14: CONTEXTO DE LA ORGANIZACIÓN
A15: 1.1 | B15: Entender la organización y su contexto | D15: Iniciar la identificación y documentación de los problemas externos e internos relevantes. Establecer un enfoque básico para evaluar el contexto organizacional de manera regular. | E15: Desarrollar un marco de trabajo más estructurado para evaluar el contexto organizacional. Capacitar a más empleados en los procedimientos y asegurar la consistencia en la aplicación de los procesos documentados. | F15: Integrar completamente los procesos de evaluación del contexto en las operaciones diarias. Implementar controles y supervisión más rigurosos y regulares, utilizando métricas específicas para evaluar la efectividad. | G15: Mantener la mejora continua y revisar regularmente los KPIs para adaptarse a los cambios en el contexto organizacional. Asegurar que todos los niveles de la organización estén alineados y comprometidos con la evaluación del contexto.
A16: 1.2 | B16: Comprender las necesidades y expectativas de las partes interesadas | D16: Comenzar a identificar y documentar sistemáticamente las necesidades de las partes interesadas. Crear procedimientos básicos para la recopilación y registro de estas necesidades. | E16: Establecer un proceso más estructurado y consistente para identificar y documentar las necesidades de las partes interesadas. Asegurar que más empleados estén involucrados y capacitados en estos procedimientos. | F16: Integrar completamente los procesos de identificación de necesidades en las operaciones diarias de la organización. Implementar controles y supervisión regulares, utilizando métricas específicas para evaluar la efectividad de estos procesos. | G16: Mantener la mejora continua y revisar regularmente los KPIs para adaptarse a los cambios en las necesidades de las partes interesadas. Asegurar que todos los niveles de la organización estén alineados y comprometidos con la identificación de estas necesidades.
A17: 1.3 | B17: Determinación del alcance del sistema de gestión de seguridad de la información | D17: Iniciar la definición y documentación del alcance del SGSI, considerando los problemas externos e internos relevantes. Establecer un enfoque básico y sistemático para esta determinación. | E17: Desarrollar un marco más estructurado para la determinación del alcance del SGSI. Capacitar a más empleados en estos procedimientos y asegurar la consistencia en la aplicación de los procesos documentados. | F17: Integrar completamente los procesos de determinación del alcance del SGSI en las operaciones diarias de la organización. Implementar controles y supervisión regulares, utilizando métricas específicas para evaluar la efectividad de estos procesos. | G17: Mantener la mejora continua y revisar regularmente los KPIs para adaptarse a los cambios en el alcance del SGSI. Asegurar que todos los niveles de la organización estén alineados y comprometidos con la determinación del alcance.
A18: 1.4 | B18: Sistema de gestión de seguridad de la información | D18: Comenzar a documentar los procesos y actividades del SGSI. Establecer un enfoque básico y sistemático para la gestión de la seguridad de la información, incluyendo la identificación de riesgos y controles necesarios. | E18: Desarrollar un marco más estructurado y consistente para la implementación del SGSI. Capacitar a más empleados en estos procedimientos y asegurar la consistencia en la aplicación de los procesos documentados. | F18: Integrar completamente el SGSI en las operaciones diarias de la organización. Implementar controles y supervisión regulares, utilizando métricas específicas para evaluar la efectividad del SGSI y su alineación con los objetivos organizacionales. | G18: Mantener la mejora continua y revisar regularmente los KPIs para adaptarse a los cambios en la seguridad de la información. Asegurar que todos los niveles de la organización estén alineados y comprometidos con el SGSI.
A19: 2. | B19: LIDERAZGO
A20: 2.1 | B20: Liderazgo y compromiso | D20: Establecer un compromiso formal de la alta dirección con el SGSI. Desarrollar y comunicar una visión clara para la seguridad de la información. Asegurar la participación activa de la alta dirección en las iniciativas de seguridad. | E20: Asegurar que el compromiso de la alta dirección sea consistente y visible. Involucrar a más miembros de la alta dirección en las actividades de seguridad y establecer métricas para medir su participación activa. | F20: Integrar completamente el compromiso de la alta dirección en los procesos organizacionales. Establecer revisiones periódicas para evaluar el compromiso y la participación de la alta dirección en el SGSI. | G20: Mantener la mejora continua y revisar regularmente los KPIs para adaptarse a los cambios en el entorno de seguridad. Asegurar que todos los niveles de la alta dirección estén alineados y comprometidos con el SGSI.
A21: 2.2 | B21: Política | D21: Desarrollar y documentar una política de seguridad de la información. Asegurar que la política esté alineada con los objetivos organizacionales y sea comunicada a todos los empleados. | E21: Revisar y mejorar la política de seguridad para asegurar su aplicación consistente. Establecer procedimientos claros y capacitar a los empleados en la implementación y seguimiento de la política. | F21: Integrar completamente la política de seguridad en los procesos organizacionales. Establecer revisiones periódicas para evaluar y actualizar la política, asegurando su alineación continua con los objetivos de seguridad y las necesidades organizacionales. | G21: Mantener la mejora continua y revisar regularmente los KPIs para adaptar la política a los cambios en el entorno de seguridad. Asegurar que todos los empleados comprendan y sigan la política de seguridad.
A22: 2.3 | B22: Funciones, responsabilidades y autoridades de la organización | D22: Definir y documentar claramente las funciones, responsabilidades y autoridades relacionadas con la seguridad de la información. Comunicar estos roles a todos los empleados y asegurar su comprensión. | E22: Revisar y mejorar la definición de roles y responsabilidades para asegurar su aplicación consistente. Establecer procedimientos claros y capacitar a los empleados en sus funciones y responsabilidades específicas. | F22: Integrar completamente las funciones, responsabilidades y autoridades en los procesos organizacionales. Establecer revisiones periódicas para evaluar y actualizar las definiciones, asegurando su alineación continua con los objetivos organizacionales. | G22: Mantener la mejora continua y revisar regularmente los KPIs para adaptar las funciones, responsabilidades y autoridades a los cambios en el entorno organizacional. Asegurar que todos los empleados comprendan y sigan sus funciones y responsabilidades.
A23: 3. | B23: PLANIFICACIÓN
A24: 3.1 | B24: Acciones para abordar riesgos y oportunidades | D24: Identificar y documentar riesgos y oportunidades. Establecer un enfoque básico para evaluar y abordar riesgos y oportunidades de manera regular. | E24: Desarrollar un marco de trabajo más estructurado y consistente para abordar riesgos y oportunidades. Capacitar a más empleados en estos procedimientos. | F24: Integrar completamente las acciones para abordar riesgos y oportunidades en los procesos organizacionales. Implementar controles y supervisión regulares. | G24: Mantener la mejora continua y revisar regularmente los KPIs para adaptarse a los cambios en los riesgos y oportunidades. Asegurar que todos los niveles de la organización estén alineados y comprometidos con la gestión de riesgos y oportunidades.
A25: 3.2 | B25: Objetivos de Seguridad de la Información y planificación para alcanzarlos | D25: Definir y documentar claramente los objetivos de seguridad de la información. Asegurar que los objetivos estén alineados con los objetivos organizacionales y sean comunicados a todos los empleados. | E25: Revisar y mejorar los objetivos de seguridad para asegurar su aplicación consistente. Establecer procedimientos claros y capacitar a los empleados en la implementación y seguimiento de los objetivos. | F25: Integrar completamente los objetivos de seguridad en los procesos organizacionales. Establecer revisiones periódicas para evaluar y actualizar los objetivos, asegurando su alineación continua con los objetivos de seguridad y las necesidades organizacionales. | G25: Mantener la mejora continua y revisar regularmente los KPIs para adaptar los objetivos a los cambios en el entorno de seguridad. Asegurar que todos los empleados comprendan y trabajen hacia los objetivos de seguridad.
A26: 4. | B26: SOPORTE
A27: 4.1 | B27: Recursos | D27: Identificar y documentar los recursos necesarios para la seguridad de la información. Asegurar la provisión adecuada de estos recursos para todas las áreas relevantes. | E27: Desarrollar un plan de recursos más estructurado y consistente. Asegurar que los recursos estén disponibles de manera regular y no dependan de individuos específicos. | F27: Integrar completamente la asignación de recursos en los procesos organizacionales. Establecer controles y supervisión regulares para asegurar la provisión continua de recursos adecuados. | G27: Mantener la mejora continua y revisar regularmente los KPIs para asegurar que los recursos se adapten a las necesidades cambiantes de la seguridad de la información.
A28: 4.2 | B28: Competencia | D28: Definir y documentar los requisitos de competencia necesarios. Establecer procedimientos para evaluar y asegurar la competencia del personal en materia de seguridad de la información. | E28: Desarrollar un enfoque más estructurado y consistente para la evaluación y aseguramiento de competencias. Capacitar a más empleados en estos procedimientos. | F28: Integrar completamente los procesos de evaluación y aseguramiento de competencias en las operaciones diarias. Establecer controles y supervisión regulares. | G28: Mantener la mejora continua y revisar regularmente los KPIs para asegurar que las competencias se adapten a las necesidades cambiantes de la seguridad de la información.
A29: 4.3 | B29: Conciencia | D29: Desarrollar y documentar un programa de concienciación sobre seguridad de la información. Asegurar que todos los empleados comprendan la importancia de la seguridad y sus responsabilidades. | E29: Establecer un programa de concienciación más estructurado y consistente. Asegurar que la concienciación sea regular y no dependa de individuos específicos. | F29: Integrar completamente las actividades de concienciación en los procesos organizacionales. Establecer controles y supervisión regulares para asegurar la efectividad de la concienciación. | G29: Mantener la mejora continua y revisar regularmente los KPIs para asegurar que la concienciación se adapte a las necesidades cambiantes de la seguridad de la información.
A30: 4.4 | B30: Comunicación | D30: Establecer y documentar procedimientos de comunicación sobre seguridad de la información. Asegurar que la información relevante se comunique de manera oportuna y efectiva. | E30: Desarrollar un enfoque más estructurado y consistente para la comunicación sobre seguridad de la información. Capacitar a más empleados en estos procedimientos. | F30: Integrar completamente los procedimientos de comunicación en los procesos organizacionales. Establecer controles y supervisión regulares para asegurar la efectividad de la comunicación. | G30: Mantener la mejora continua y revisar regularmente los KPIs para asegurar que la comunicación se adapte a las necesidades cambiantes de la seguridad de la información.
A31: 4.5 | B31: Información documentada | D31: Establecer y documentar procedimientos para la gestión y control de la información. Asegurar que la documentación sea precisa, accesible y se mantenga actualizada. | E31: Desarrollar un enfoque más estructurado y consistente para la gestión de la información. Capacitar a más empleados en estos procedimientos y asegurar la consistencia en su aplicación. | F31: Integrar completamente los procedimientos de gestión de la información en los procesos organizacionales. Establecer controles y supervisión regulares para asegurar la efectividad de la gestión. | G31: Mantener la mejora continua y revisar regularmente los KPIs para asegurar que la gestión de la información se adapte a las necesidades cambiantes de la organización.
A32: 5. | B32: OPERACIÓN
A33: 5.1 | B33: Planificación y control operativo | D33: Iniciar la planificación y documentación sistemática de las operaciones de seguridad de la información. Establecer un enfoque básico para el control operativo. | E33: Desarrollar un marco más estructurado y consistente para la planificación y control operativo. Capacitar a más empleados en estos procedimientos. | F33: Integrar completamente la planificación y el control operativo en los procesos organizacionales. Implementar controles y supervisión regulares para asegurar la efectividad de las operaciones. | G33: Mantener la mejora continua y revisar regularmente los KPIs para adaptarse a los cambios en las operaciones. Asegurar que todos los niveles de la organización estén alineados y comprometidos con la planificación y el control operativo.
A34: 5.2 | B34: Evaluación de riesgos de Seguridad de la Información | D34: Comenzar a identificar y documentar sistemáticamente los riesgos de seguridad de la información. Establecer un enfoque básico para la evaluación regular de riesgos. | E34: Desarrollar un marco de trabajo más estructurado y consistente para la evaluación de riesgos. Capacitar a más empleados en estos procedimientos y asegurar la consistencia en la evaluación. | F34: Integrar completamente los procesos de evaluación de riesgos en las operaciones diarias de la organización. Implementar controles y supervisión regulares para asegurar la efectividad de la evaluación de riesgos. | G34: Mantener la mejora continua y revisar regularmente los KPIs para adaptarse a los cambios en el entorno de riesgos. Asegurar que todos los niveles de la organización estén alineados y comprometidos con la evaluación de riesgos.
A35: 5.3 | B35: Tratamiento de riesgos de Seguridad de la Información | D35: Iniciar la identificación y documentación sistemática de los riesgos de seguridad de la información. Establecer un enfoque básico para el tratamiento regular de riesgos. | E35: Desarrollar un marco de trabajo más estructurado y consistente para el tratamiento de riesgos. Capacitar a más empleados en estos procedimientos y asegurar la consistencia en el tratamiento. | F35: Integrar completamente los procesos de tratamiento de riesgos en las operaciones diarias de la organización. Implementar controles y supervisión regulares para asegurar la efectividad del tratamiento de riesgos. | G35: Mantener la mejora continua y revisar regularmente los KPIs para adaptarse a los cambios en el entorno de riesgos. Asegurar que todos los niveles de la organización estén alineados y comprometidos con el tratamiento de riesgos.
A36: 6. | B36: EVALUACIÓN DEL DESEMPEÑO
A37: 6.1 | B37: Seguimiento, medición, análisis y evaluación | D37: Establecer y documentar procedimientos formales para el seguimiento, medición, análisis y evaluación de la seguridad de la información. | E37: Desarrollar un enfoque más estructurado y consistente para estas actividades. Capacitar a más empleados y asegurar la regularidad y precisión en la recopilación de datos. | F37: Integrar completamente estas actividades en los procesos organizacionales. Implementar controles y supervisión regulares para asegurar la exactitud y utilidad de los datos recopilados. | G37: Mantener la mejora continua y revisar regularmente los KPIs para adaptarse a los cambios en el entorno y mejorar la toma de decisiones sobre la seguridad de la información.
A38: 6.2 | B38: Auditoría Interna | D38: Establecer y documentar un programa formal de auditoría interna para evaluar la efectividad del SGSI. Asegurar que las auditorías se realicen de manera regular y sistemática. | E38: Desarrollar un enfoque más estructurado y consistente para las auditorías internas. Capacitar a más empleados en estos procedimientos y asegurar la regularidad y consistencia en las evaluaciones. | F38: Integrar completamente las auditorías internas en los procesos organizacionales. Implementar controles y supervisión regulares para asegurar la efectividad de las auditorías. | G38: Mantener la mejora continua y revisar regularmente los KPIs para adaptarse a los cambios en el entorno y mejorar la evaluación de la efectividad del SGSI a través de las auditorías internas.
A39: 6.3 | B39: Revisión por la dirección | D39: Establecer y documentar un procedimiento formal para la revisión del SGSI por parte de la alta dirección. Asegurar que las revisiones se realicen de manera regular y sistemática. | E39: Desarrollar un enfoque más estructurado y consistente para las revisiones por la dirección. Capacitar a más miembros de la alta dirección en estos procedimientos y asegurar la regularidad en las revisiones. | F39: Integrar completamente las revisiones del SGSI en los procesos de la alta dirección. Implementar controles y supervisión regulares para asegurar la efectividad de las revisiones. | G39: Mantener la mejora continua y revisar regularmente los KPIs para adaptarse a los cambios en el entorno y mejorar la evaluación de la idoneidad, adecuación y efectividad del SGSI a través de las revisiones por la dirección.
A40: 7. | B40: MEJORA
A41: 7.1 | B41: Mejora continua | D41: Iniciar la identificación y documentación sistemática de oportunidades de mejora en la seguridad de la información. Establecer un enfoque básico para la mejora continua. | E41: Desarrollar un enfoque más estructurado y consistente para la mejora continua. Capacitar a más empleados en estos procedimientos y asegurar la regularidad y sistematicidad en las mejoras. | F41: Integrar completamente las actividades de mejora continua en los procesos organizacionales. Implementar controles y supervisión regulares para asegurar la efectividad de las mejoras. | G41: Mantener la mejora continua y revisar regularmente los KPIs para adaptarse a los cambios en el entorno y asegurar la mejora constante en la seguridad de la información.
A42: 7.2 | B42: No conformidad y acción correctiva | D42: Establecer y documentar un procedimiento formal para la gestión de no conformidades y acciones correctivas. Asegurar que todas las no conformidades se identifiquen y aborden sistemáticamente. | E42: Desarrollar un enfoque más estructurado y consistente para la gestión de no conformidades y acciones correctivas. Capacitar a más empleados en estos procedimientos y asegurar la regularidad en la resolución de no conformidades. | F42: Integrar completamente los procesos de gestión de no conformidades y acciones correctivas en los procesos organizacionales. Implementar controles y supervisión regulares para asegurar la efectividad de las resoluciones. | G42: Mantener la mejora continua y revisar regularmente los KPIs para adaptarse a los cambios en el entorno y asegurar la resolución constante y efectiva de las no conformidades.

Sheet Resumen y valoración
B1: Matriz para medir el nivel actual del Sistemas de gestión de seguridad de la información según ISO 27001:2022
A5: Entidad (o cliente): | C5: ID. | D5: Período de auditoría de: 1/01/2023 | E5: Hasta: 31/12/2023 | G5: Referencia
A6: Preparado por: | D6: Revisado por: | G6: XX-XX
A7: Supervisado por: | D7: Aprobado por:
A10: OBJETIVO
A11: El objetivo de la matriz es proporcionar una visión consolidada del estado actual del sistema de gestión de la seguridad de la información (SGSI) en la organización, permitiendo evaluar de manera integral el contexto de la organización, el liderazgo, la planificación, el soporte, la oparación y evaluación, y la mejora del Sistema de gestión del riesgo y seguridad según la norma ISO 27001:2022. Esta hoja tiene como objetivo resumir los resultados de las evaluaciones individuales, una valoración global y recomendaciones a tener en cuenta para alcanzar el siguiente nivel y así facilitar la toma de decisiones estratégicas para mejorar la gestión del riesgo en la organización.
A13: RESUMEN PUNTAJE
D15: Puntaje | E15: Nivel de madurez
A16: No. | B16: ÍNDICE DE MADUREZ DE LA NORMA ISO 27001:2022 | D16: =IFERROR(AVERAGE(D17,D22,D26,D29,D35,D39,D43),"") -> 2.252381 | E16: =+IF(D16<=1,'Guía de uso'!$B$21,IF(D16<=2,'Guía de uso'!$B$22,IF(D16<=3,'Guía de uso'!$B$23,IF(D16<=4,'Guía de uso'!$B$24,"No ha seleccionado")))) -> Definido | F16: Riesgo | G16: Descripción del riesgo | H16: Recomendaciones y/o acciones para alcanzar el siguiente nivel
A17: 1. | B17: Contexto de la organización | C17: Nivel actual | D17: =IFERROR(AVERAGE(D18:D21),"") -> 2.5 | E17: =+IF(D17<=1,'Guía de uso'!$B$21,IF(D17<=2,'Guía de uso'!$B$22,IF(D17<=3,'Guía de uso'!$B$23,IF(D17<=4,'Guía de uso'!$B$24,"No ha seleccionado")))) -> Definido
A18: 1.1 | B18: Entender la organización y su contexto | C18: =+IF('Check - Contexto'!G17=TRUE,'Check - Contexto'!D17,IF('Check - Contexto'!G18=TRUE,'Check - Contexto'!D18,IF('Check - Contexto'!G19=TRUE,'Check - Contexto'!D19,IF('Check - Contexto'!G20=TRUE,'Check - Contexto'!D20,"")))) -> Existen esfuerzos por documentar los procesos, pero la implementación es inconsistente y no sistemática. | D18: =IF('Check - Contexto'!$G$15="SELECCIONE SOLAMENTE UN NIVEL","SELECCIONE SOLAMENTE UN NIVEL",SUM('Check - Contexto'!$J$17:$J$20)) -> 2 | E18: =+IF(D18<=1,'Guía de uso'!$B$21,IF(D18<=2,'Guía de uso'!$B$22,IF(D18<=3,'Guía de uso'!$B$23,IF(D18<=4,'Guía de uso'!$B$24,"No ha seleccionado")))) -> Repetible | F18: Insignificante | H18: =IFERROR(HLOOKUP(E18,Recomendaciones!$A$8:$G$58,8,FALSE),"") -> Desarrollar un marco de trabajo más estructurado para evaluar el contexto organizacional. Capacitar a más empleados en los procedimientos y asegurar la consistencia en la aplicación de los procesos documentados.
A19: 1.2 | B19: Comprender las necesidades y expectativas de las partes interesadas | C19: =+IF('Check - Contexto'!G23=TRUE,'Check - Contexto'!B23,IF('Check - Contexto'!G24=TRUE,'Check - Contexto'!B24,IF('Check - Contexto'!G25=TRUE,'Check - Contexto'!B25,IF('Check - Contexto'!G26=TRUE,'Check - Contexto'!B26,"")))) -> Procesos documentados y metodologías estándar aseguran la identificación y entendimiento adecuados. | D19: =IF('Check - Contexto'!$G$21="SELECCIONE SOLAMENTE UN NIVEL","SELECCIONE SOLAMENTE UN NIVEL",SUM('Check - Contexto'!$J$23:$J$26)) -> 3 | E19: =+IF(D19<=1,'Guía de uso'!$B$21,IF(D19<=2,'Guía de uso'!$B$22,IF(D19<=3,'Guía de uso'!$B$23,IF(D19<=4,'Guía de uso'!$B$24,"No ha seleccionado")))) -> Definido | F19: Medio | H19: =IFERROR(HLOOKUP(E19,Recomendaciones!$A$8:$G$58,9,FALSE),"") -> Integrar completamente los procesos de identificación de necesidades en las operaciones diarias de la organización. Implementar controles y supervisión regulares, utilizando métricas específicas para evaluar la efectividad de estos procesos.
A20: 1.3 | B20: Determinación del alcance del sistema de gestión de seguridad de la información | C20: =+IF('Check - Contexto'!G29=TRUE,'Check - Contexto'!B29,IF('Check - Contexto'!G30=TRUE,'Check - Contexto'!B30,IF('Check - Contexto'!G31=TRUE,'Check - Contexto'!B31,IF('Check - Contexto'!G32=TRUE,'Check - Contexto'!B32,"")))) -> El alcance del SGSI está bien documentado y definido, siguiendo metodologías estándar. | D20: =IF('Check - Contexto'!$G$27="SELECCIONE SOLAMENTE UN NIVEL","SELECCIONE SOLAMENTE UN NIVEL",SUM('Check - Contexto'!$J$29:$J$32)) -> 3 | E20: =+IF(D20<=1,'Guía de uso'!$B$21,IF(D20<=2,'Guía de uso'!$B$22,IF(D20<=3,'Guía de uso'!$B$23,IF(D20<=4,'Guía de uso'!$B$24,"No ha seleccionado")))) -> Definido | F20: Bajo | H20: =IFERROR(HLOOKUP(E20,Recomendaciones!$A$8:$G$58,10,FALSE),"") -> Integrar completamente los procesos de determinación del alcance del SGSI en las operaciones diarias de la organización. Implementar controles y supervisión regulares, utilizando métricas específicas para evaluar la efectividad de estos procesos.
A21: 1.4 | B21: Sistema de gestión de seguridad de la información | C21: =+IF('Check - Contexto'!G35=TRUE,'Check - Contexto'!D35,IF('Check - Contexto'!G36=TRUE,'Check - Contexto'!D36,IF('Check - Contexto'!G37=TRUE,'Check - Contexto'!D37,IF('Check - Contexto'!G38=TRUE,'Check - Contexto'!D38,"")))) -> Existen esfuerzos por documentar el SGSI, pero la implementación es inconsistente y depende en gran medida de individuos específicos para su aplicación efectiva. | D21: =IF('Check - Contexto'!$G$33="SELECCIONE SOLAMENTE UN NIVEL","SELECCIONE SOLAMENTE UN NIVEL",SUM('Check - Contexto'!$J$35:$J$38)) -> 2 | E21: =+IF(D21<=1,'Guía de uso'!$B$21,IF(D21<=2,'Guía de uso'!$B$22,IF(D21<=3,'Guía de uso'!$B$23,IF(D21<=4,'Guía de uso'!$B$24,"No ha seleccionado")))) -> Repetible | F21: Alto | H21: =IFERROR(HLOOKUP(E21,Recomendaciones!$A$8:$G$58,11,FALSE),"") -> Desarrollar un marco más estructurado y consistente para la implementación del SGSI. Capacitar a más empleados en estos procedimientos y asegurar la consistencia en la aplicación de los procesos documentados.
A22: 2. | B22: Liderazgo | C22: Nivel actual | D22: =IFERROR(AVERAGE(D23:D25),"") -> 2.3333333 | E22: =+IF(D22<=1,'Guía de uso'!$B$21,IF(D22<=2,'Guía de uso'!$B$22,IF(D22<=3,'Guía de uso'!$B$23,IF(D22<=4,'Guía de uso'!$B$24,"No ha seleccionado")))) -> Definido
A23: 2.1 | B23: Liderazgo y compromiso | C23: =+IF('Check - Liderazgo'!G17=TRUE,'Check - Liderazgo'!D17,IF('Check - Liderazgo'!G18=TRUE,'Check - Liderazgo'!D18,IF('Check - Liderazgo'!G19=TRUE,'Check - Liderazgo'!D19,IF('Check - Liderazgo'!G20=TRUE,'Check - Liderazgo'!D20,"")))) -> Existen esfuerzos documentados para demostrar el compromiso de la alta dirección, pero la aplicación es inconsistente. | D23: =IF('Check - Liderazgo'!$G$15="SELECCIONE SOLAMENTE UN NIVEL","SELECCIONE SOLAMENTE UN NIVEL",SUM('Check - Liderazgo'!$J$17:$J$20)) -> 2 | E23: =+IF(D23<=1,'Guía de uso'!$B$21,IF(D23<=2,'Guía de uso'!$B$22,IF(D23<=3,'Guía de uso'!$B$23,IF(D23<=4,'Guía de uso'!$B$24,"No ha seleccionado")))) -> Repetible | F23: Crítico | H23: =IFERROR(HLOOKUP(E23,Recomendaciones!$A$8:$G$58,13,FALSE),"") -> Asegurar que el compromiso de la alta dirección sea consistente y visible. Involucrar a más miembros de la alta dirección en las actividades de seguridad y establecer métricas para medir su participación activa.
A24: 2.2 | B24: Política | C24: =+IF('Check - Liderazgo'!G23=TRUE,'Check - Liderazgo'!D23,IF('Check - Liderazgo'!G24=TRUE,'Check - Liderazgo'!D24,IF('Check - Liderazgo'!G25=TRUE,'Check - Liderazgo'!D25,IF('Check - Liderazgo'!G26=TRUE,'Check - Liderazgo'!D26,"")))) -> La política de seguridad está claramente documentada, siguiendo metodologías estándar, con un nivel básico de control y supervisión para asegurar su aplicación. | D24: =IF('Check - Liderazgo'!$G$21="SELECCIONE SOLAMENTE UN NIVEL","SELECCIONE SOLAMENTE UN NIVEL",SUM('Check - Liderazgo'!$J$23:$J$26)) -> 3 | E24: =+IF(D24<=1,'Guía de uso'!$B$21,IF(D24<=2,'Guía de uso'!$B$22,IF(D24<=3,'Guía de uso'!$B$23,IF(D24<=4,'Guía de uso'!$B$24,"No ha seleccionado")))) -> Definido | F24: Bajo | H24: =IFERROR(HLOOKUP(E24,Recomendaciones!$A$8:$G$58,14,FALSE),"") -> Integrar completamente la política de seguridad en los procesos organizacionales. Establecer revisiones periódicas para evaluar y actualizar la política, asegurando su alineación continua con los objetivos de seguridad y las necesidades organizacionales.
A25: 2.3 | B25: Funciones, responsabilidades y autoridades de la organización | C25: =+IF('Check - Liderazgo'!G29=TRUE,'Check - Liderazgo'!D29,IF('Check - Liderazgo'!G30=TRUE,'Check - Liderazgo'!D30,IF('Check - Liderazgo'!G31=TRUE,'Check - Liderazgo'!D31,IF('Check - Liderazgo'!G32=TRUE,'Check - Liderazgo'!D32,"")))) -> Se han definido y documentado roles y responsabilidades básicas, pero su aplicación es irregular y depende de individuos específicos. | D25: =IF('Check - Liderazgo'!$G$27="SELECCIONE SOLAMENTE UN NIVEL","SELECCIONE SOLAMENTE UN NIVEL",SUM('Check - Liderazgo'!$J$29:$J$32)) -> 2 | E25: =+IF(D25<=1,'Guía de uso'!$B$21,IF(D25<=2,'Guía de uso'!$B$22,IF(D25<=3,'Guía de uso'!$B$23,IF(D25<=4,'Guía de uso'!$B$24,"No ha seleccionado")))) -> Repetible | F25: Bajo | H25: =IFERROR(HLOOKUP(E25,Recomendaciones!$A$8:$G$58,15,FALSE),"") -> Revisar y mejorar la definición de roles y responsabilidades para asegurar su aplicación consistente. Establecer procedimientos claros y capacitar a los empleados en sus funciones y responsabilidades específicas.
A26: 3. | B26: Planificación | C26: Nivel actual | D26: =IFERROR(AVERAGE(D27:D28),"") -> 2 | E26: =+IF(D26<=1,'Guía de uso'!$B$21,IF(D26<=2,'Guía de uso'!$B$22,IF(D26<=3,'Guía de uso'!$B$23,IF(D26<=4,'Guía de uso'!$B$24,"No ha seleccionado")))) -> Repetible
A27: 3.1 | B27: Acciones para abordar riesgos y oportunidades | C27: =+IF('Check - Planificación'!G17=TRUE,'Check - Planificación'!D17,IF('Check - Planificación'!G18=TRUE,'Check - Planificación'!D18,IF('Check - Planificación'!G19=TRUE,'Check - Planificación'!D19,IF('Check - Planificación'!G20=TRUE,'Check - Planificación'!D20,"")))) -> Se han documentado acciones para abordar riesgos y oportunidades, pero la implementación depende de individuos específicos y no es sistemática. | D27: =IF('Check - Planificación'!$G$15="SELECCIONE SOLAMENTE UN NIVEL","SELECCIONE SOLAMENTE UN NIVEL",SUM('Check - Planificación'!$J$17:$J$20)) -> 2 | E27: =+IF(D27<=1,'Guía de uso'!$B$21,IF(D27<=2,'Guía de uso'!$B$22,IF(D27<=3,'Guía de uso'!$B$23,IF(D27<=4,'Guía de uso'!$B$24,"No ha seleccionado")))) -> Repetible | F27: Crítico | H27: =IFERROR(HLOOKUP(E27,Recomendaciones!$A$8:$G$58,17,FALSE),"") -> Desarrollar un marco de trabajo más estructurado y consistente para abordar riesgos y oportunidades. Capacitar a más empleados en estos procedimientos.
A28: 3.2 | B28: Objetivos de Seguridad de la Información y planificación para alcanzarlos | C28: =+IF('Check - Planificación'!G23=TRUE,'Check - Planificación'!D23,IF('Check - Planificación'!G24=TRUE,'Check - Planificación'!D24,IF('Check - Planificación'!G25=TRUE,'Check - Planificación'!D25,IF('Check - Planificación'!G26=TRUE,'Check - Planificación'!D26,"")))) -> Se han establecido y documentado objetivos, pero la implementación y el seguimiento dependen de individuos específicos y no son sistemáticos. | D28: =IF('Check - Planificación'!$G$21="SELECCIONE SOLAMENTE UN NIVEL","SELECCIONE SOLAMENTE UN NIVEL",SUM('Check - Planificación'!$J$23:$J$26)) -> 2 | E28: =+IF(D28<=1,'Guía de uso'!$B$21,IF(D28<=2,'Guía de uso'!$B$22,IF(D28<=3,'Guía de uso'!$B$23,IF(D28<=4,'Guía de uso'!$B$24,"No ha seleccionado")))) -> Repetible | F28: Alto | H28: =IFERROR(HLOOKUP(E28,Recomendaciones!$A$8:$G$58,18,FALSE),"") -> Revisar y mejorar los objetivos de seguridad para asegurar su aplicación consistente. Establecer procedimientos claros y capacitar a los empleados en la implementación y seguimiento de los objetivos.
A29: 4. | B29: Soporte | C29: Nivel actual | D29: =IFERROR(AVERAGE(D30:D34),"") -> 2.6 | E29: =+IF(D29<=1,'Guía de uso'!$B$21,IF(D29<=2,'Guía de uso'!$B$22,IF(D29<=3,'Guía de uso'!$B$23,IF(D29<=4,'Guía de uso'!$B$24,"No ha seleccionado")))) -> Definido
A30: 4.1 | B30: Recursos | C30: =+IF('Check - Soporte'!G17=TRUE,'Check - Soporte'!D17,IF('Check - Soporte'!G18=TRUE,'Check - Soporte'!D18,IF('Check - Soporte'!G19=TRUE,'Check - Soporte'!D19,IF('Check - Soporte'!G20=TRUE,'Check - Soporte'!D20,"")))) -> Los recursos necesarios para la seguridad de la información están claramente definidos y asignados, siguiendo metodologías estándar, con un nivel básico de control. | D30: =IF('Check - Soporte'!$G$15="SELECCIONE SOLAMENTE UN NIVEL","SELECCIONE SOLAMENTE UN NIVEL",SUM('Check - Soporte'!$J$17:$J$20)) -> 3 | E30: =+IF(D30<=1,'Guía de uso'!$B$21,IF(D30<=2,'Guía de uso'!$B$22,IF(D30<=3,'Guía de uso'!$B$23,IF(D30<=4,'Guía de uso'!$B$24,"No ha seleccionado")))) -> Definido | F30: Insignificante | H30: =IFERROR(HLOOKUP(E30,Recomendaciones!$A$8:$G$58,20,FALSE),"") -> Integrar completamente la asignación de recursos en los procesos organizacionales. Establecer controles y supervisión regulares para asegurar la provisión continua de recursos adecuados.
A31: 4.2 | B31: Competencia | C31: =+IF('Check - Soporte'!G23=TRUE,'Check - Soporte'!D23,IF('Check - Soporte'!G24=TRUE,'Check - Soporte'!D24,IF('Check - Soporte'!G25=TRUE,'Check - Soporte'!D25,IF('Check - Soporte'!G26=TRUE,'Check - Soporte'!D26,"")))) -> Los requisitos de competencia están claramente definidos y se evalúan siguiendo metodologías estándar, con un nivel básico de control y supervisión. | D31: =IF('Check - Soporte'!$G$21="SELECCIONE SOLAMENTE UN NIVEL","SELECCIONE SOLAMENTE UN NIVEL",SUM('Check - Soporte'!$J$23:$J$26)) -> 3 | E31: =+IF(D31<=1,'Guía de uso'!$B$21,IF(D31<=2,'Guía de uso'!$B$22,IF(D31<=3,'Guía de uso'!$B$23,IF(D31<=4,'Guía de uso'!$B$24,"No ha seleccionado")))) -> Definido | F31: Medio | H31: =IFERROR(HLOOKUP(E31,Recomendaciones!$A$8:$G$58,21,FALSE),"") -> Integrar completamente los procesos de evaluación y aseguramiento de competencias en las operaciones diarias. Establecer controles y supervisión regulares.
A32: 4.3 | B32: Conciencia | C32: =+IF('Check - Soporte'!G29=TRUE,'Check - Soporte'!D29,IF('Check - Soporte'!G30=TRUE,'Check - Soporte'!D30,IF('Check - Soporte'!G31=TRUE,'Check - Soporte'!D31,IF('Check - Soporte'!G32=TRUE,'Check - Soporte'!D32,"")))) -> Hay intentos por concienciar al personal sobre la seguridad, pero estos esfuerzos son irregulares y dependen de individuos específicos. | D32: =IF('Check - Soporte'!$G$27="SELECCIONE SOLAMENTE UN NIVEL","SELECCIONE SOLAMENTE UN NIVEL",SUM('Check - Soporte'!$J$29:$J$32)) -> 2 | E32: =+IF(D32<=1,'Guía de uso'!$B$21,IF(D32<=2,'Guía de uso'!$B$22,IF(D32<=3,'Guía de uso'!$B$23,IF(D32<=4,'Guía de uso'!$B$24,"No ha seleccionado")))) -> Repetible | F32: Bajo | H32: =IFERROR(HLOOKUP(E32,Recomendaciones!$A$8:$G$58,22,FALSE),"") -> Establecer un programa de concienciación más estructurado y consistente. Asegurar que la concienciación sea regular y no dependa de individuos específicos.
A33: 4.4 | B33: Comunicación | C33: =+IF('Check - Soporte'!G35=TRUE,'Check - Soporte'!D35,IF('Check - Soporte'!G36=TRUE,'Check - Soporte'!D36,IF('Check - Soporte'!G37=TRUE,'Check - Soporte'!D37,IF('Check - Soporte'!G38=TRUE,'Check - Soporte'!D38,"")))) -> Los procedimientos de comunicación están claramente documentados y definidos, siguiendo metodologías estándar, con un nivel básico de control y supervisión. | D33: =IF('Check - Soporte'!$G$33="SELECCIONE SOLAMENTE UN NIVEL","SELECCIONE SOLAMENTE UN NIVEL",SUM('Check - Soporte'!$J$35:$J$38)) -> 3 | E33: =+IF(D33<=1,'Guía de uso'!$B$21,IF(D33<=2,'Guía de uso'!$B$22,IF(D33<=3,'Guía de uso'!$B$23,IF(D33<=4,'Guía de uso'!$B$24,"No ha seleccionado")))) -> Definido | F33: Alto | H33: =IFERROR(HLOOKUP(E33,Recomendaciones!$A$8:$G$58,23,FALSE),"") -> Integrar completamente los procedimientos de comunicación en los procesos organizacionales. Establecer controles y supervisión regulares para asegurar la efectividad de la comunicación.
A34: 4.5 | B34: Información documentada | C34: =+IF('Check - Soporte'!G41=TRUE,'Check - Soporte'!D41,IF('Check - Soporte'!G42=TRUE,'Check - Soporte'!D42,IF('Check - Soporte'!G43=TRUE,'Check - Soporte'!D43,IF('Check - Soporte'!G44=TRUE,'Check - Soporte'!D44,"")))) -> Se han establecido procedimientos básicos para la gestión de la información, pero su implementación es irregular y depende de individuos específicos. | D34: =IF('Check - Soporte'!$G$39="SELECCIONE SOLAMENTE UN NIVEL","SELECCIONE SOLAMENTE UN NIVEL",SUM('Check - Soporte'!$J$41:$J$44)) -> 2 | E34: =+IF(D34<=1,'Guía de uso'!$B$21,IF(D34<=2,'Guía de uso'!$B$22,IF(D34<=3,'Guía de uso'!$B$23,IF(D34<=4,'Guía de uso'!$B$24,"No ha seleccionado")))) -> Repetible | F34: Alto | H34: =IFERROR(HLOOKUP(E34,Recomendaciones!$A$8:$G$58,24,FALSE),"") -> Desarrollar un enfoque más estructurado y consistente para la gestión de la información. Capacitar a más empleados en estos procedimientos y asegurar la consistencia en su aplicación.
A35: 5. | B35: Operación | C35: Nivel actual | D35: =IFERROR(AVERAGE(D36:D38),"") -> 2 | E35: =+IF(D35<=1,'Guía de uso'!$B$21,IF(D35<=2,'Guía de uso'!$B$22,IF(D35<=3,'Guía de uso'!$B$23,IF(D35<=4,'Guía de uso'!$B$24,"No ha seleccionado")))) -> Repetible
A36: 5.1 | B36: Planificación y control operativo | C36: =+IF('Check - Operación'!G17=TRUE,'Check - Operación'!D17,IF('Check - Operación'!G18=TRUE,'Check - Operación'!D18,IF('Check - Operación'!G19=TRUE,'Check - Operación'!D19,IF('Check - Operación'!G20=TRUE,'Check - Operación'!D20,"")))) -> Se ha comenzado a planificar y controlar las operaciones, pero la implementación es irregular y depende en gran medida de individuos específicos. | D36: =IF('Check - Operación'!$G$15="SELECCIONE SOLAMENTE UN NIVEL","SELECCIONE SOLAMENTE UN NIVEL",SUM('Check - Operación'!$J$17:$J$20)) -> 2 | E36: =+IF(D36<=1,'Guía de uso'!$B$21,IF(D36<=2,'Guía de uso'!$B$22,IF(D36<=3,'Guía de uso'!$B$23,IF(D36<=4,'Guía de uso'!$B$24,"No ha seleccionado")))) -> Repetible | F36: Insignificante | H36: =IFERROR(HLOOKUP(E36,Recomendaciones!$A$8:$G$58,26,FALSE),"") -> Desarrollar un marco más estructurado y consistente para la planificación y control operativo. Capacitar a más empleados en estos procedimientos.
A37: 5.2 | B37: Evaluación de riesgos de Seguridad de la Información | C37: =+IF('Check - Operación'!G23=TRUE,'Check - Operación'!D23,IF('Check - Operación'!G24=TRUE,'Check - Operación'!D24,IF('Check - Operación'!G25=TRUE,'Check - Operación'!D25,IF('Check - Operación'!G26=TRUE,'Check - Operación'!D26,"")))) -> Se han comenzado a evaluar los riesgos, pero la implementación es irregular y depende de individuos específicos para su efectividad. | D37: =IF('Check - Operación'!$G$21="SELECCIONE SOLAMENTE UN NIVEL","SELECCIONE SOLAMENTE UN NIVEL",SUM('Check - Operación'!$J$23:$J$26)) -> 2 | E37: =+IF(D37<=1,'Guía de uso'!$B$21,IF(D37<=2,'Guía de uso'!$B$22,IF(D37<=3,'Guía de uso'!$B$23,IF(D37<=4,'Guía de uso'!$B$24,"No ha seleccionado")))) -> Repetible | F37: Medio | H37: =IFERROR(HLOOKUP(E37,Recomendaciones!$A$8:$G$58,27,FALSE),"") -> Desarrollar un marco de trabajo más estructurado y consistente para la evaluación de riesgos. Capacitar a más empleados en estos procedimientos y asegurar la consistencia en la evaluación.
A38: 5.3 | B38: Tratamiento de riesgos de Seguridad de la Información | C38: =+IF('Check - Operación'!G29=TRUE,'Check - Operación'!D29,IF('Check - Operación'!G30=TRUE,'Check - Operación'!D30,IF('Check - Operación'!G31=TRUE,'Check - Operación'!D31,IF('Check - Operación'!G32=TRUE,'Check - Operación'!D32,"")))) -> Se han documentado acciones para el tratamiento de riesgos, pero la implementación es irregular y depende de individuos específicos para su efectividad. | D38: =IF('Check - Operación'!$G$27="SELECCIONE SOLAMENTE UN NIVEL","SELECCIONE SOLAMENTE UN NIVEL",SUM('Check - Operación'!$J$29:$J$32)) -> 2 | E38: =+IF(D38<=1,'Guía de uso'!$B$21,IF(D38<=2,'Guía de uso'!$B$22,IF(D38<=3,'Guía de uso'!$B$23,IF(D38<=4,'Guía de uso'!$B$24,"No ha seleccionado")))) -> Repetible | F38: Bajo | H38: =IFERROR(HLOOKUP(E38,Recomendaciones!$A$8:$G$58,28,FALSE),"") -> Desarrollar un marco de trabajo más estructurado y consistente para el tratamiento de riesgos. Capacitar a más empleados en estos procedimientos y asegurar la consistencia en el tratamiento.
A39: 6. | B39: Evaluación del desempeño | C39: Nivel actual | D39: =IFERROR(AVERAGE(D40:D42),"") -> 2.3333333 | E39: =+IF(D39<=1,'Guía de uso'!$B$21,IF(D39<=2,'Guía de uso'!$B$22,IF(D39<=3,'Guía de uso'!$B$23,IF(D39<=4,'Guía de uso'!$B$24,"No ha seleccionado")))) -> Definido
A40: 6.1 | B40: Seguimiento, medición, análisis y evaluación | C40: =+IF('Check - Evaluación'!G17=TRUE,'Check - Evaluación'!D17,IF('Check - Evaluación'!G18=TRUE,'Check - Evaluación'!D18,IF('Check - Evaluación'!G19=TRUE,'Check - Evaluación'!D19,IF('Check - Evaluación'!G20=TRUE,'Check - Evaluación'!D20,"")))) -> Las actividades están claramente documentadas, siguiendo metodologías estándar, con un nivel básico de control y supervisión para asegurar la exactitud y utilidad de los datos. | D40: =IF('Check - Evaluación'!$G$15="SELECCIONE SOLAMENTE UN NIVEL","SELECCIONE SOLAMENTE UN NIVEL",SUM('Check - Evaluación'!$J$17:$J$20)) -> 3 | E40: =+IF(D40<=1,'Guía de uso'!$B$21,IF(D40<=2,'Guía de uso'!$B$22,IF(D40<=3,'Guía de uso'!$B$23,IF(D40<=4,'Guía de uso'!$B$24,"No ha seleccionado")))) -> Definido | F40: Insignificante | H40: =IFERROR(HLOOKUP(E40,Recomendaciones!$A$8:$G$58,30,FALSE),"") -> Integrar completamente estas actividades en los procesos organizacionales. Implementar controles y supervisión regulares para asegurar la exactitud y utilidad de los datos recopilados.
A41: 6.2 | B41: Auditoría Interna | C41: =+IF('Check - Evaluación'!G23=TRUE,'Check - Evaluación'!D23,IF('Check - Evaluación'!G24=TRUE,'Check - Evaluación'!D24,IF('Check - Evaluación'!G25=TRUE,'Check - Evaluación'!D25,IF('Check - Evaluación'!G26=TRUE,'Check - Evaluación'!D26,"")))) -> Existen esfuerzos para realizar auditorías internas, pero son irregulares y dependen de individuos específicos, lo que afecta la consistencia de las evaluaciones. | D41: =IF('Check - Evaluación'!$G$21="SELECCIONE SOLAMENTE UN NIVEL","SELECCIONE SOLAMENTE UN NIVEL",SUM('Check - Evaluación'!$J$23:$J$26)) -> 2 | E41: =+IF(D41<=1,'Guía de uso'!$B$21,IF(D41<=2,'Guía de uso'!$B$22,IF(D41<=3,'Guía de uso'!$B$23,IF(D41<=4,'Guía de uso'!$B$24,"No ha seleccionado")))) -> Repetible | F41: Medio | H41: =IFERROR(HLOOKUP(E41,Recomendaciones!$A$8:$G$58,31,FALSE),"") -> Desarrollar un enfoque más estructurado y consistente para las auditorías internas. Capacitar a más empleados en estos procedimientos y asegurar la regularidad y consistencia en las evaluaciones.
A42: 6.3 | B42: Revisión por la dirección | C42: =+IF('Check - Evaluación'!G29=TRUE,'Check - Evaluación'!D29,IF('Check - Evaluación'!G30=TRUE,'Check - Evaluación'!D30,IF('Check - Evaluación'!G31=TRUE,'Check - Evaluación'!D31,IF('Check - Evaluación'!G32=TRUE,'Check - Evaluación'!D32,"")))) -> Existen esfuerzos para revisar el SGSI, pero son irregulares y dependen de individuos específicos, lo que afecta la consistencia y utilidad de las revisiones. | D42: =IF('Check - Evaluación'!$G$27="SELECCIONE SOLAMENTE UN NIVEL","SELECCIONE SOLAMENTE UN NIVEL",SUM('Check - Evaluación'!$J$29:$J$32)) -> 2 | E42: =+IF(D42<=1,'Guía de uso'!$B$21,IF(D42<=2,'Guía de uso'!$B$22,IF(D42<=3,'Guía de uso'!$B$23,IF(D42<=4,'Guía de uso'!$B$24,"No ha seleccionado")))) -> Repetible | F42: Bajo | H42: =IFERROR(HLOOKUP(E42,Recomendaciones!$A$8:$G$58,32,FALSE),"") -> Desarrollar un enfoque más estructurado y consistente para las revisiones por la dirección. Capacitar a más miembros de la alta dirección en estos procedimientos y asegurar la regularidad en las revisiones.
A43: 7. | B43: Mejora | C43: Nivel actual | D43: =IFERROR(AVERAGE(D44:D45),"") -> 2 | E43: =+IF(D43<=1,'Guía de uso'!$B$21,IF(D43<=2,'Guía de uso'!$B$22,IF(D43<=3,'Guía de uso'!$B$23,IF(D43<=4,'Guía de uso'!$B$24,"No ha seleccionado")))) -> Repetible
A44: 7.1 | B44: Mejora continua | C44: =+IF('Check - Mejora'!G17=TRUE,'Check - Mejora'!D17,IF('Check - Mejora'!G18=TRUE,'Check - Mejora'!D18,IF('Check - Mejora'!G19=TRUE,'Check - Mejora'!D19,IF('Check - Mejora'!G20=TRUE,'Check - Mejora'!D20,"")))) -> Existen esfuerzos para identificar y realizar mejoras, pero son irregulares y dependen de individuos específicos, afectando la consistencia del progreso. | D44: =IF('Check - Mejora'!$G$15="SELECCIONE SOLAMENTE UN NIVEL","SELECCIONE SOLAMENTE UN NIVEL",SUM('Check - Mejora'!$J$17:$J$20)) -> 2 | E44: =+IF(D44<=1,'Guía de uso'!$B$21,IF(D44<=2,'Guía de uso'!$B$22,IF(D44<=3,'Guía de uso'!$B$23,IF(D44<=4,'Guía de uso'!$B$24,"No ha seleccionado")))) -> Repetible | F44: Insignificante | H44: =IFERROR(HLOOKUP(E44,Recomendaciones!$A$8:$G$58,34,FALSE),"") -> Desarrollar un enfoque más estructurado y consistente para la mejora continua. Capacitar a más empleados en estos procedimientos y asegurar la regularidad y sistematicidad en las mejoras.
A45: 7.2 | B45: No conformidad y acción correctiva | C45: =+IF('Check - Mejora'!G23=TRUE,'Check - Mejora'!D23,IF('Check - Mejora'!G24=TRUE,'Check - Mejora'!D24,IF('Check - Mejora'!G25=TRUE,'Check - Mejora'!D25,IF('Check - Mejora'!G26=TRUE,'Check - Mejora'!D26,"")))) -> Existen esfuerzos para gestionar no conformidades y tomar acciones correctivas, pero son irregulares y dependen de individuos específicos, afectando la consistencia de la resolución. | D45: =IF('Check - Mejora'!$G$21="SELECCIONE SOLAMENTE UN NIVEL","SELECCIONE SOLAMENTE UN NIVEL",SUM('Check - Mejora'!$J$23:$J$26)) -> 2 | E45: =+IF(D45<=1,'Guía de uso'!$B$21,IF(D45<=2,'Guía de uso'!$B$22,IF(D45<=3,'Guía de uso'!$B$23,IF(D45<=4,'Guía de uso'!$B$24,"No ha seleccionado")))) -> Repetible | F45: Medio | H45: =IFERROR(HLOOKUP(E45,Recomendaciones!$A$8:$G$58,35,FALSE),"") -> Desarrollar un enfoque más estructurado y consistente para la gestión de no conformidades y acciones correctivas. Capacitar a más empleados en estos procedimientos y asegurar la regularidad en la resolución de no conformidades.
A47: CONCLUSIÓN Y/O OBSERVACIONES ADICIONALES

Sheet Gráfico
B2: Resumen de resultados y gráfico radial para la evaluación del nivel actual del Sistema de Gestión de Riesgos y Seguridad según ISO 27001:2022
A5: Entidad (o cliente): | C5: ID. | D5: Período de auditoría de: 1/01/2023 | F5: Referencia
A6: Preparado por: | D6: Revisado por: | F6: XX-XX
A7: Supervisado por: | D7: Aprobado por:
A10: RESUMEN DE RESULTADOS ASPECTOS DEL SISTEMA DE GESTIÓN DE RIESGOS Y SEGURIDAD
A12: Componente | E12: Nivel actual | F12: Objetivo
A13: ISO 31000 | B13: Contexto de la organización | C13: =+'Resumen y valoración'!B18 -> Entender la organización y su contexto | E13: =+'Resumen y valoración'!D18 -> 2 | F13: 4
C14: =+'Resumen y valoración'!B19 -> Comprender las necesidades y expectativas de las partes interesadas | E14: =+'Resumen y valoración'!D19 -> 3 | F14: 4
C15: =+'Resumen y valoración'!B20 -> Determinación del alcance del sistema de gestión de seguridad de la información | E15: =+'Resumen y valoración'!D20 -> 3 | F15: 4
C16: =+'Resumen y valoración'!B21 -> Sistema de gestión de seguridad de la información | E16: =+'Resumen y valoración'!D21 -> 2 | F16: 4
B17: Liderazgo | C17: =+'Resumen y valoración'!B23 -> Liderazgo y compromiso | E17: =+'Resumen y valoración'!D23 -> 2 | F17: 4
C18: =+'Resumen y valoración'!B24 -> Política | E18: =+'Resumen y valoración'!D24 -> 3 | F18: 4
C19: =+'Resumen y valoración'!B25 -> Funciones, responsabilidades y autoridades de la organización | E19: =+'Resumen y valoración'!D25 -> 2 | F19: 4
B20: Planificación | C20: =+'Resumen y valoración'!B27 -> Acciones para abordar riesgos y oportunidades | E20: =+'Resumen y valoración'!D27 -> 2 | F20: 4
C21: =+'Resumen y valoración'!B28 -> Objetivos de Seguridad de la Información y planificación para alcanzarlos | E21: =+'Resumen y valoración'!D28 -> 2 | F21: 4
B22: Soporte | C22: =+'Resumen y valoración'!B30 -> Recursos | E22: =+'Resumen y valoración'!D30 -> 3 | F22: 4
C23: =+'Resumen y valoración'!B31 -> Competencia | E23: =+'Resumen y valoración'!D31 -> 3 | F23: 4
C24: =+'Resumen y valoración'!B32 -> Conciencia | E24: =+'Resumen y valoración'!D32 -> 2 | F24: 4
C25: =+'Resumen y valoración'!B33 -> Comunicación | E25: =+'Resumen y valoración'!D33 -> 3 | F25: 4
C26: =+'Resumen y valoración'!B34 -> Información documentada | E26: =+'Resumen y valoración'!D34 -> 2 | F26: 4
B27: Operación | C27: =+'Resumen y valoración'!B36 -> Planificación y control operativo | E27: =+'Resumen y valoración'!D36 -> 2 | F27: 4
C28: =+'Resumen y valoración'!B37 -> Evaluación de riesgos de Seguridad de la Información | E28: =+'Resumen y valoración'!D37 -> 2 | F28: 4
C29: =+'Resumen y valoración'!B38 -> Tratamiento de riesgos de Seguridad de la Información | E29: =+'Resumen y valoración'!D38 -> 2 | F29: 4
B30: Evaluación de desempeño | C30: =+'Resumen y valoración'!B40 -> Seguimiento, medición, análisis y evaluación | E30: =+'Resumen y valoración'!D40 -> 3 | F30: 4
C31: =+'Resumen y valoración'!B41 -> Auditoría Interna | E31: =+'Resumen y valoración'!D41 -> 2 | F31: 4
C32: =+'Resumen y valoración'!B42 -> Revisión por la dirección | E32: =+'Resumen y valoración'!D42 -> 2 | F32: 4
B33: Mejora | C33: =+'Resumen y valoración'!B44 -> Mejora continua | E33: =+'Resumen y valoración'!D44 -> 2 | F33: 4
C34: =+'Resumen y valoración'!B45 -> No conformidad y acción correctiva | E34: =+'Resumen y valoración'!D45 -> 2 | F34: 4
A36: GRÁFICO RADIAL
A52: CONCLUSIÓN Y/O OBSERVACIONES ADICIONALES
